Compiled from "AbstractContainerScreen.java"
public abstract class net.minecraft.client.gui.screens.inventory.AbstractContainerScreen<T extends net.minecraft.world.inventory.AbstractContainerMenu> extends net.minecraft.client.gui.screens.Screen implements net.minecraft.client.gui.screens.inventory.MenuAccess<T> {
  public static final net.minecraft.resources.Identifier INVENTORY_LOCATION;

  protected static final int BACKGROUND_TEXTURE_WIDTH;

  protected static final int BACKGROUND_TEXTURE_HEIGHT;

  protected static final int DEFAULT_IMAGE_WIDTH;

  protected static final int DEFAULT_IMAGE_HEIGHT;

  protected final int imageWidth;

  protected final int imageHeight;

  protected int titleLabelX;

  protected int titleLabelY;

  protected int inventoryLabelX;

  protected int inventoryLabelY;

  protected final T menu;

  protected final net.minecraft.network.chat.Component playerInventoryTitle;

  protected net.minecraft.world.inventory.Slot hoveredSlot;

  protected int leftPos;

  protected int topPos;

  protected final java.util.Set<net.minecraft.world.inventory.Slot> quickCraftSlots;

  protected boolean isQuickCrafting;

  public net.minecraft.client.gui.screens.inventory.AbstractContainerScreen(T, net.minecraft.world.entity.player.Inventory, net.minecraft.network.chat.Component);
    Code:
       0: aload_0
       1: aload_1
       2: aload_2
       3: aload_3
       4: sipush        176
       7: sipush        166
      10: invokespecial #1                  // Method "<init>":(Lnet/minecraft/world/inventory/AbstractContainerMenu;Lnet/minecraft/world/entity/player/Inventory;Lnet/minecraft/network/chat/Component;II)V
      13: return

  public net.minecraft.client.gui.screens.inventory.AbstractContainerScreen(T, net.minecraft.world.entity.player.Inventory, net.minecraft.network.chat.Component, int, int);
    Code:
       0: aload_0
       1: aload_3
       2: invokespecial #7                  // Method net/minecraft/client/gui/screens/Screen."<init>":(Lnet/minecraft/network/chat/Component;)V
       5: aload_0
       6: getstatic     #12                 // Field net/minecraft/world/item/ItemStack.EMPTY:Lnet/minecraft/world/item/ItemStack;
       9: putfield      #18                 // Field draggingItem:Lnet/minecraft/world/item/ItemStack;
      12: aload_0
      13: invokestatic  #21                 // Method com/google/common/collect/Sets.newHashSet:()Ljava/util/HashSet;
      16: putfield      #27                 // Field quickCraftSlots:Ljava/util/Set;
      19: aload_0
      20: getstatic     #12                 // Field net/minecraft/world/item/ItemStack.EMPTY:Lnet/minecraft/world/item/ItemStack;
      23: putfield      #31                 // Field lastQuickMoved:Lnet/minecraft/world/item/ItemStack;
      26: aload_0
      27: aload_1
      28: putfield      #34                 // Field menu:Lnet/minecraft/world/inventory/AbstractContainerMenu;
      31: aload_0
      32: aload_2
      33: invokevirtual #38                 // Method net/minecraft/world/entity/player/Inventory.getDisplayName:()Lnet/minecraft/network/chat/Component;
      36: putfield      #44                 // Field playerInventoryTitle:Lnet/minecraft/network/chat/Component;
      39: aload_0
      40: iload         4
      42: putfield      #48                 // Field imageWidth:I
      45: aload_0
      46: iload         5
      48: putfield      #52                 // Field imageHeight:I
      51: aload_0
      52: iconst_1
      53: putfield      #55                 // Field skipNextRelease:Z
      56: aload_0
      57: bipush        8
      59: putfield      #59                 // Field titleLabelX:I
      62: aload_0
      63: bipush        6
      65: putfield      #62                 // Field titleLabelY:I
      68: aload_0
      69: bipush        8
      71: putfield      #65                 // Field inventoryLabelX:I
      74: aload_0
      75: iload         5
      77: bipush        94
      79: isub
      80: putfield      #68                 // Field inventoryLabelY:I
      83: aload_0
      84: new           #71                 // class java/util/ArrayList
      87: dup
      88: invokespecial #73                 // Method java/util/ArrayList."<init>":()V
      91: putfield      #76                 // Field itemSlotMouseActions:Ljava/util/List;
      94: return

  protected void init();
    Code:
       0: aload_0
       1: aload_0
       2: getfield      #80                 // Field width:I
       5: aload_0
       6: getfield      #48                 // Field imageWidth:I
       9: isub
      10: iconst_2
      11: idiv
      12: putfield      #83                 // Field leftPos:I
      15: aload_0
      16: aload_0
      17: getfield      #86                 // Field height:I
      20: aload_0
      21: getfield      #52                 // Field imageHeight:I
      24: isub
      25: iconst_2
      26: idiv
      27: putfield      #89                 // Field topPos:I
      30: aload_0
      31: getfield      #76                 // Field itemSlotMouseActions:Ljava/util/List;
      34: invokeinterface #92,  1           // InterfaceMethod java/util/List.clear:()V
      39: aload_0
      40: new           #97                 // class net/minecraft/client/gui/BundleMouseActions
      43: dup
      44: aload_0
      45: getfield      #99                 // Field minecraft:Lnet/minecraft/client/Minecraft;
      48: invokespecial #103                // Method net/minecraft/client/gui/BundleMouseActions."<init>":(Lnet/minecraft/client/Minecraft;)V
      51: invokevirtual #106                // Method addItemSlotMouseAction:(Lnet/minecraft/client/gui/ItemSlotMouseAction;)V
      54: return

  protected void addItemSlotMouseAction(net.minecraft.client.gui.ItemSlotMouseAction);
    Code:
       0: aload_0
       1: getfield      #76                 // Field itemSlotMouseActions:Ljava/util/List;
       4: aload_1
       5: invokeinterface #110,  2          // InterfaceMethod java/util/List.add:(Ljava/lang/Object;)Z
      10: pop
      11: return

  public void extractRenderState(net.minecraft.client.gui.GuiGraphicsExtractor, int, int, float);
    Code:
       0: aload_0
       1: aload_1
       2: iload_2
       3: iload_3
       4: fload         4
       6: invokevirtual #114                // Method extractContents:(Lnet/minecraft/client/gui/GuiGraphicsExtractor;IIF)V
       9: aload_0
      10: aload_1
      11: iload_2
      12: iload_3
      13: invokevirtual #118                // Method extractCarriedItem:(Lnet/minecraft/client/gui/GuiGraphicsExtractor;II)V
      16: aload_0
      17: aload_1
      18: invokevirtual #122                // Method extractSnapbackItem:(Lnet/minecraft/client/gui/GuiGraphicsExtractor;)V
      21: aload_0
      22: aload_1
      23: iload_2
      24: iload_3
      25: invokevirtual #126                // Method extractTooltip:(Lnet/minecraft/client/gui/GuiGraphicsExtractor;II)V
      28: return

  public void extractContents(net.minecraft.client.gui.GuiGraphicsExtractor, int, int, float);
    Code:
       0: aload_0
       1: getfield      #83                 // Field leftPos:I
       4: istore        5
       6: aload_0
       7: getfield      #89                 // Field topPos:I
      10: istore        6
      12: aload_0
      13: aload_1
      14: iload_2
      15: iload_3
      16: fload         4
      18: invokespecial #129                // Method net/minecraft/client/gui/screens/Screen.extractRenderState:(Lnet/minecraft/client/gui/GuiGraphicsExtractor;IIF)V
      21: aload_1
      22: invokevirtual #132                // Method net/minecraft/client/gui/GuiGraphicsExtractor.pose:()Lorg/joml/Matrix3x2fStack;
      25: invokevirtual #138                // Method org/joml/Matrix3x2fStack.pushMatrix:()Lorg/joml/Matrix3x2fStack;
      28: pop
      29: aload_1
      30: invokevirtual #132                // Method net/minecraft/client/gui/GuiGraphicsExtractor.pose:()Lorg/joml/Matrix3x2fStack;
      33: iload         5
      35: i2f
      36: iload         6
      38: i2f
      39: invokevirtual #143                // Method org/joml/Matrix3x2fStack.translate:(FF)Lorg/joml/Matrix3x2f;
      42: pop
      43: aload_0
      44: aload_1
      45: iload_2
      46: iload_3
      47: invokevirtual #147                // Method extractLabels:(Lnet/minecraft/client/gui/GuiGraphicsExtractor;II)V
      50: aload_0
      51: getfield      #150                // Field hoveredSlot:Lnet/minecraft/world/inventory/Slot;
      54: astore        7
      56: aload_0
      57: aload_0
      58: iload_2
      59: i2d
      60: iload_3
      61: i2d
      62: invokevirtual #154                // Method getHoveredSlot:(DD)Lnet/minecraft/world/inventory/Slot;
      65: putfield      #150                // Field hoveredSlot:Lnet/minecraft/world/inventory/Slot;
      68: aload_0
      69: aload_1
      70: invokevirtual #158                // Method extractSlotHighlightBack:(Lnet/minecraft/client/gui/GuiGraphicsExtractor;)V
      73: aload_0
      74: aload_1
      75: iload_2
      76: iload_3
      77: invokevirtual #161                // Method extractSlots:(Lnet/minecraft/client/gui/GuiGraphicsExtractor;II)V
      80: aload_0
      81: aload_1
      82: invokevirtual #164                // Method extractSlotHighlightFront:(Lnet/minecraft/client/gui/GuiGraphicsExtractor;)V
      85: aload         7
      87: ifnull        105
      90: aload         7
      92: aload_0
      93: getfield      #150                // Field hoveredSlot:Lnet/minecraft/world/inventory/Slot;
      96: if_acmpeq     105
      99: aload_0
     100: aload         7
     102: invokevirtual #167                // Method onStopHovering:(Lnet/minecraft/world/inventory/Slot;)V
     105: getstatic     #171                // Field net/neoforged/neoforge/common/NeoForge.EVENT_BUS:Lnet/neoforged/bus/api/IEventBus;
     108: new           #177                // class net/neoforged/neoforge/client/event/ContainerScreenEvent$Render$Foreground
     111: dup
     112: aload_0
     113: aload_1
     114: iload_2
     115: iload_3
     116: invokespecial #179                // Method net/neoforged/neoforge/client/event/ContainerScreenEvent$Render$Foreground."<init>":(Lnet/minecraft/client/gui/screens/inventory/AbstractContainerScreen;Lnet/minecraft/client/gui/GuiGraphicsExtractor;II)V
     119: invokeinterface #182,  2          // InterfaceMethod net/neoforged/bus/api/IEventBus.post:(Lnet/neoforged/bus/api/Event;)Lnet/neoforged/bus/api/Event;
     124: pop
     125: aload_1
     126: invokevirtual #132                // Method net/minecraft/client/gui/GuiGraphicsExtractor.pose:()Lorg/joml/Matrix3x2fStack;
     129: invokevirtual #188                // Method org/joml/Matrix3x2fStack.popMatrix:()Lorg/joml/Matrix3x2fStack;
     132: pop
     133: return

  public void extractCarriedItem(net.minecraft.client.gui.GuiGraphicsExtractor, int, int);
    Code:
       0: aload_0
       1: getfield      #18                 // Field draggingItem:Lnet/minecraft/world/item/ItemStack;
       4: invokevirtual #191                // Method net/minecraft/world/item/ItemStack.isEmpty:()Z
       7: ifeq          20
      10: aload_0
      11: getfield      #34                 // Field menu:Lnet/minecraft/world/inventory/AbstractContainerMenu;
      14: invokevirtual #195                // Method net/minecraft/world/inventory/AbstractContainerMenu.getCarried:()Lnet/minecraft/world/item/ItemStack;
      17: goto          24
      20: aload_0
      21: getfield      #18                 // Field draggingItem:Lnet/minecraft/world/item/ItemStack;
      24: astore        4
      26: aload         4
      28: invokevirtual #191                // Method net/minecraft/world/item/ItemStack.isEmpty:()Z
      31: ifne          171
      34: bipush        8
      36: istore        5
      38: aload_0
      39: getfield      #18                 // Field draggingItem:Lnet/minecraft/world/item/ItemStack;
      42: invokevirtual #191                // Method net/minecraft/world/item/ItemStack.isEmpty:()Z
      45: ifeq          53
      48: bipush        8
      50: goto          55
      53: bipush        16
      55: istore        6
      57: aconst_null
      58: astore        7
      60: aload_0
      61: getfield      #18                 // Field draggingItem:Lnet/minecraft/world/item/ItemStack;
      64: invokevirtual #191                // Method net/minecraft/world/item/ItemStack.isEmpty:()Z
      67: ifne          98
      70: aload_0
      71: getfield      #201                // Field isSplittingStack:Z
      74: ifeq          98
      77: aload         4
      79: aload         4
      81: invokevirtual #204                // Method net/minecraft/world/item/ItemStack.getCount:()I
      84: i2f
      85: fconst_2
      86: fdiv
      87: invokestatic  #208                // Method net/minecraft/util/Mth.ceil:(F)I
      90: invokevirtual #214                // Method net/minecraft/world/item/ItemStack.copyWithCount:(I)Lnet/minecraft/world/item/ItemStack;
      93: astore        4
      95: goto          150
      98: aload_0
      99: getfield      #218                // Field isQuickCrafting:Z
     102: ifeq          150
     105: aload_0
     106: getfield      #27                 // Field quickCraftSlots:Ljava/util/Set;
     109: invokeinterface #221,  1          // InterfaceMethod java/util/Set.size:()I
     114: iconst_1
     115: if_icmple     150
     118: aload         4
     120: aload_0
     121: getfield      #226                // Field quickCraftingRemainder:I
     124: invokevirtual #214                // Method net/minecraft/world/item/ItemStack.copyWithCount:(I)Lnet/minecraft/world/item/ItemStack;
     127: astore        4
     129: aload         4
     131: invokevirtual #191                // Method net/minecraft/world/item/ItemStack.isEmpty:()Z
     134: ifeq          150
     137: getstatic     #229                // Field net/minecraft/ChatFormatting.YELLOW:Lnet/minecraft/ChatFormatting;
     140: invokestatic  #235                // Method java/lang/String.valueOf:(Ljava/lang/Object;)Ljava/lang/String;
     143: invokedynamic #241,  0            // InvokeDynamic #0:makeConcatWithConstants:(Ljava/lang/String;)Ljava/lang/String;
     148: astore        7
     150: aload_1
     151: invokevirtual #245                // Method net/minecraft/client/gui/GuiGraphicsExtractor.nextStratum:()V
     154: aload_0
     155: aload_1
     156: aload         4
     158: iload_2
     159: bipush        8
     161: isub
     162: iload_3
     163: iload         6
     165: isub
     166: aload         7
     168: invokevirtual #248                // Method extractFloatingItem:(Lnet/minecraft/client/gui/GuiGraphicsExtractor;Lnet/minecraft/world/item/ItemStack;IILjava/lang/String;)V
     171: return

  public void extractSnapbackItem(net.minecraft.client.gui.GuiGraphicsExtractor);
    Code:
       0: aload_0
       1: getfield      #252                // Field snapbackData:Lnet/minecraft/client/gui/screens/inventory/AbstractContainerScreen$SnapbackData;
       4: ifnull        143
       7: invokestatic  #256                // Method net/minecraft/util/Util.getMillis:()J
      10: aload_0
      11: getfield      #252                // Field snapbackData:Lnet/minecraft/client/gui/screens/inventory/AbstractContainerScreen$SnapbackData;
      14: getfield      #262                // Field net/minecraft/client/gui/screens/inventory/AbstractContainerScreen$SnapbackData.time:J
      17: lsub
      18: l2f
      19: ldc_w         #268                // float 100.0f
      22: fdiv
      23: fconst_0
      24: fconst_1
      25: invokestatic  #269                // Method net/minecraft/util/Mth.clamp:(FFF)F
      28: fstore_2
      29: aload_0
      30: getfield      #252                // Field snapbackData:Lnet/minecraft/client/gui/screens/inventory/AbstractContainerScreen$SnapbackData;
      33: getfield      #273                // Field net/minecraft/client/gui/screens/inventory/AbstractContainerScreen$SnapbackData.end:Lorg/joml/Vector2i;
      36: getfield      #277                // Field org/joml/Vector2i.x:I
      39: aload_0
      40: getfield      #252                // Field snapbackData:Lnet/minecraft/client/gui/screens/inventory/AbstractContainerScreen$SnapbackData;
      43: getfield      #282                // Field net/minecraft/client/gui/screens/inventory/AbstractContainerScreen$SnapbackData.start:Lorg/joml/Vector2i;
      46: getfield      #277                // Field org/joml/Vector2i.x:I
      49: isub
      50: istore_3
      51: aload_0
      52: getfield      #252                // Field snapbackData:Lnet/minecraft/client/gui/screens/inventory/AbstractContainerScreen$SnapbackData;
      55: getfield      #273                // Field net/minecraft/client/gui/screens/inventory/AbstractContainerScreen$SnapbackData.end:Lorg/joml/Vector2i;
      58: getfield      #285                // Field org/joml/Vector2i.y:I
      61: aload_0
      62: getfield      #252                // Field snapbackData:Lnet/minecraft/client/gui/screens/inventory/AbstractContainerScreen$SnapbackData;
      65: getfield      #282                // Field net/minecraft/client/gui/screens/inventory/AbstractContainerScreen$SnapbackData.start:Lorg/joml/Vector2i;
      68: getfield      #285                // Field org/joml/Vector2i.y:I
      71: isub
      72: istore        4
      74: aload_0
      75: getfield      #252                // Field snapbackData:Lnet/minecraft/client/gui/screens/inventory/AbstractContainerScreen$SnapbackData;
      78: getfield      #282                // Field net/minecraft/client/gui/screens/inventory/AbstractContainerScreen$SnapbackData.start:Lorg/joml/Vector2i;
      81: getfield      #277                // Field org/joml/Vector2i.x:I
      84: iload_3
      85: i2f
      86: fload_2
      87: fmul
      88: f2i
      89: iadd
      90: istore        5
      92: aload_0
      93: getfield      #252                // Field snapbackData:Lnet/minecraft/client/gui/screens/inventory/AbstractContainerScreen$SnapbackData;
      96: getfield      #282                // Field net/minecraft/client/gui/screens/inventory/AbstractContainerScreen$SnapbackData.start:Lorg/joml/Vector2i;
      99: getfield      #285                // Field org/joml/Vector2i.y:I
     102: iload         4
     104: i2f
     105: fload_2
     106: fmul
     107: f2i
     108: iadd
     109: istore        6
     111: aload_1
     112: invokevirtual #245                // Method net/minecraft/client/gui/GuiGraphicsExtractor.nextStratum:()V
     115: aload_0
     116: aload_1
     117: aload_0
     118: getfield      #252                // Field snapbackData:Lnet/minecraft/client/gui/screens/inventory/AbstractContainerScreen$SnapbackData;
     121: getfield      #288                // Field net/minecraft/client/gui/screens/inventory/AbstractContainerScreen$SnapbackData.item:Lnet/minecraft/world/item/ItemStack;
     124: iload         5
     126: iload         6
     128: aconst_null
     129: invokevirtual #248                // Method extractFloatingItem:(Lnet/minecraft/client/gui/GuiGraphicsExtractor;Lnet/minecraft/world/item/ItemStack;IILjava/lang/String;)V
     132: fload_2
     133: fconst_1
     134: fcmpl
     135: iflt          143
     138: aload_0
     139: aconst_null
     140: putfield      #252                // Field snapbackData:Lnet/minecraft/client/gui/screens/inventory/AbstractContainerScreen$SnapbackData;
     143: return

  protected void extractSlots(net.minecraft.client.gui.GuiGraphicsExtractor, int, int);
    Code:
       0: aload_0
       1: getfield      #34                 // Field menu:Lnet/minecraft/world/inventory/AbstractContainerMenu;
       4: getfield      #291                // Field net/minecraft/world/inventory/AbstractContainerMenu.slots:Lnet/minecraft/core/NonNullList;
       7: invokevirtual #295                // Method net/minecraft/core/NonNullList.iterator:()Ljava/util/Iterator;
      10: astore        4
      12: aload         4
      14: invokeinterface #301,  1          // InterfaceMethod java/util/Iterator.hasNext:()Z
      19: ifeq          54
      22: aload         4
      24: invokeinterface #306,  1          // InterfaceMethod java/util/Iterator.next:()Ljava/lang/Object;
      29: checkcast     #310                // class net/minecraft/world/inventory/Slot
      32: astore        5
      34: aload         5
      36: invokevirtual #312                // Method net/minecraft/world/inventory/Slot.isActive:()Z
      39: ifeq          51
      42: aload_0
      43: aload_1
      44: aload         5
      46: iload_2
      47: iload_3
      48: invokevirtual #315                // Method extractSlot:(Lnet/minecraft/client/gui/GuiGraphicsExtractor;Lnet/minecraft/world/inventory/Slot;II)V
      51: goto          12
      54: return

  public boolean mouseScrolled(double, double, double, double);
    Code:
       0: aload_0
       1: getfield      #150                // Field hoveredSlot:Lnet/minecraft/world/inventory/Slot;
       4: ifnull        97
       7: aload_0
       8: getfield      #150                // Field hoveredSlot:Lnet/minecraft/world/inventory/Slot;
      11: invokevirtual #319                // Method net/minecraft/world/inventory/Slot.hasItem:()Z
      14: ifeq          97
      17: aload_0
      18: getfield      #76                 // Field itemSlotMouseActions:Ljava/util/List;
      21: invokeinterface #322,  1          // InterfaceMethod java/util/List.iterator:()Ljava/util/Iterator;
      26: astore        9
      28: aload         9
      30: invokeinterface #301,  1          // InterfaceMethod java/util/Iterator.hasNext:()Z
      35: ifeq          97
      38: aload         9
      40: invokeinterface #306,  1          // InterfaceMethod java/util/Iterator.next:()Ljava/lang/Object;
      45: checkcast     #323                // class net/minecraft/client/gui/ItemSlotMouseAction
      48: astore        10
      50: aload         10
      52: aload_0
      53: getfield      #150                // Field hoveredSlot:Lnet/minecraft/world/inventory/Slot;
      56: invokeinterface #325,  2          // InterfaceMethod net/minecraft/client/gui/ItemSlotMouseAction.matches:(Lnet/minecraft/world/inventory/Slot;)Z
      61: ifeq          94
      64: aload         10
      66: dload         5
      68: dload         7
      70: aload_0
      71: getfield      #150                // Field hoveredSlot:Lnet/minecraft/world/inventory/Slot;
      74: getfield      #329                // Field net/minecraft/world/inventory/Slot.index:I
      77: aload_0
      78: getfield      #150                // Field hoveredSlot:Lnet/minecraft/world/inventory/Slot;
      81: invokevirtual #332                // Method net/minecraft/world/inventory/Slot.getItem:()Lnet/minecraft/world/item/ItemStack;
      84: invokeinterface #335,  7          // InterfaceMethod net/minecraft/client/gui/ItemSlotMouseAction.onMouseScrolled:(DDILnet/minecraft/world/item/ItemStack;)Z
      89: ifeq          94
      92: iconst_1
      93: ireturn
      94: goto          28
      97: iconst_0
      98: ireturn

  protected void extractTooltip(net.minecraft.client.gui.GuiGraphicsExtractor, int, int);
    Code:
       0: aload_0
       1: getfield      #150                // Field hoveredSlot:Lnet/minecraft/world/inventory/Slot;
       4: ifnull        82
       7: aload_0
       8: getfield      #150                // Field hoveredSlot:Lnet/minecraft/world/inventory/Slot;
      11: invokevirtual #319                // Method net/minecraft/world/inventory/Slot.hasItem:()Z
      14: ifeq          82
      17: aload_0
      18: getfield      #150                // Field hoveredSlot:Lnet/minecraft/world/inventory/Slot;
      21: invokevirtual #332                // Method net/minecraft/world/inventory/Slot.getItem:()Lnet/minecraft/world/item/ItemStack;
      24: astore        4
      26: aload_0
      27: getfield      #34                 // Field menu:Lnet/minecraft/world/inventory/AbstractContainerMenu;
      30: invokevirtual #195                // Method net/minecraft/world/inventory/AbstractContainerMenu.getCarried:()Lnet/minecraft/world/item/ItemStack;
      33: invokevirtual #191                // Method net/minecraft/world/item/ItemStack.isEmpty:()Z
      36: ifne          48
      39: aload_0
      40: aload         4
      42: invokevirtual #361                // Method showTooltipWithItemInHand:(Lnet/minecraft/world/item/ItemStack;)Z
      45: ifeq          82
      48: aload_1
      49: aload_0
      50: getfield      #365                // Field font:Lnet/minecraft/client/gui/Font;
      53: aload_0
      54: aload         4
      56: invokevirtual #369                // Method getTooltipFromContainerItem:(Lnet/minecraft/world/item/ItemStack;)Ljava/util/List;
      59: aload         4
      61: invokevirtual #373                // Method net/minecraft/world/item/ItemStack.getTooltipImage:()Ljava/util/Optional;
      64: aload         4
      66: iload_2
      67: iload_3
      68: aload         4
      70: getstatic     #377                // Field net/minecraft/core/component/DataComponents.TOOLTIP_STYLE:Lnet/minecraft/core/component/DataComponentType;
      73: invokevirtual #383                // Method net/minecraft/world/item/ItemStack.get:(Lnet/minecraft/core/component/DataComponentType;)Ljava/lang/Object;
      76: checkcast     #387                // class net/minecraft/resources/Identifier
      79: invokevirtual #389                // Method net/minecraft/client/gui/GuiGraphicsExtractor.setTooltipForNextFrame:(Lnet/minecraft/client/gui/Font;Ljava/util/List;Ljava/util/Optional;Lnet/minecraft/world/item/ItemStack;IILnet/minecraft/resources/Identifier;)V
      82: return

  protected java.util.List<net.minecraft.network.chat.Component> getTooltipFromContainerItem(net.minecraft.world.item.ItemStack);
    Code:
       0: aload_0
       1: getfield      #99                 // Field minecraft:Lnet/minecraft/client/Minecraft;
       4: aload_1
       5: invokestatic  #416                // Method getTooltipFromItem:(Lnet/minecraft/client/Minecraft;Lnet/minecraft/world/item/ItemStack;)Ljava/util/List;
       8: areturn

  protected void extractLabels(net.minecraft.client.gui.GuiGraphicsExtractor, int, int);
    Code:
       0: aload_1
       1: aload_0
       2: getfield      #365                // Field font:Lnet/minecraft/client/gui/Font;
       5: aload_0
       6: getfield      #443                // Field title:Lnet/minecraft/network/chat/Component;
       9: aload_0
      10: getfield      #59                 // Field titleLabelX:I
      13: aload_0
      14: getfield      #62                 // Field titleLabelY:I
      17: ldc_w         #446                // int -12566464
      20: iconst_0
      21: invokevirtual #447                // Method net/minecraft/client/gui/GuiGraphicsExtractor.text:(Lnet/minecraft/client/gui/Font;Lnet/minecraft/network/chat/Component;IIIZ)V
      24: aload_1
      25: aload_0
      26: getfield      #365                // Field font:Lnet/minecraft/client/gui/Font;
      29: aload_0
      30: getfield      #44                 // Field playerInventoryTitle:Lnet/minecraft/network/chat/Component;
      33: aload_0
      34: getfield      #65                 // Field inventoryLabelX:I
      37: aload_0
      38: getfield      #68                 // Field inventoryLabelY:I
      41: ldc_w         #446                // int -12566464
      44: iconst_0
      45: invokevirtual #447                // Method net/minecraft/client/gui/GuiGraphicsExtractor.text:(Lnet/minecraft/client/gui/Font;Lnet/minecraft/network/chat/Component;IIIZ)V
      48: return

  protected void extractSlot(net.minecraft.client.gui.GuiGraphicsExtractor, net.minecraft.world.inventory.Slot, int, int);
    Code:
       0: aload_2
       1: getfield      #352                // Field net/minecraft/world/inventory/Slot.x:I
       4: istore        5
       6: aload_2
       7: getfield      #353                // Field net/minecraft/world/inventory/Slot.y:I
      10: istore        6
      12: aload_2
      13: invokevirtual #332                // Method net/minecraft/world/inventory/Slot.getItem:()Lnet/minecraft/world/item/ItemStack;
      16: astore        7
      18: iconst_0
      19: istore        8
      21: aload_2
      22: aload_0
      23: getfield      #451                // Field clickedSlot:Lnet/minecraft/world/inventory/Slot;
      26: if_acmpne     50
      29: aload_0
      30: getfield      #18                 // Field draggingItem:Lnet/minecraft/world/item/ItemStack;
      33: invokevirtual #191                // Method net/minecraft/world/item/ItemStack.isEmpty:()Z
      36: ifne          50
      39: aload_0
      40: getfield      #201                // Field isSplittingStack:Z
      43: ifne          50
      46: iconst_1
      47: goto          51
      50: iconst_0
      51: istore        9
      53: aload_0
      54: getfield      #34                 // Field menu:Lnet/minecraft/world/inventory/AbstractContainerMenu;
      57: invokevirtual #195                // Method net/minecraft/world/inventory/AbstractContainerMenu.getCarried:()Lnet/minecraft/world/item/ItemStack;
      60: astore        10
      62: aconst_null
      63: astore        11
      65: aload_2
      66: aload_0
      67: getfield      #451                // Field clickedSlot:Lnet/minecraft/world/inventory/Slot;
      70: if_acmpne     115
      73: aload_0
      74: getfield      #18                 // Field draggingItem:Lnet/minecraft/world/item/ItemStack;
      77: invokevirtual #191                // Method net/minecraft/world/item/ItemStack.isEmpty:()Z
      80: ifne          115
      83: aload_0
      84: getfield      #201                // Field isSplittingStack:Z
      87: ifeq          115
      90: aload         7
      92: invokevirtual #191                // Method net/minecraft/world/item/ItemStack.isEmpty:()Z
      95: ifne          115
      98: aload         7
     100: aload         7
     102: invokevirtual #204                // Method net/minecraft/world/item/ItemStack.getCount:()I
     105: iconst_2
     106: idiv
     107: invokevirtual #214                // Method net/minecraft/world/item/ItemStack.copyWithCount:(I)Lnet/minecraft/world/item/ItemStack;
     110: astore        7
     112: goto          296
     115: aload_0
     116: getfield      #218                // Field isQuickCrafting:Z
     119: ifeq          296
     122: aload_0
     123: getfield      #27                 // Field quickCraftSlots:Ljava/util/Set;
     126: aload_2
     127: invokeinterface #454,  2          // InterfaceMethod java/util/Set.contains:(Ljava/lang/Object;)Z
     132: ifeq          296
     135: aload         10
     137: invokevirtual #191                // Method net/minecraft/world/item/ItemStack.isEmpty:()Z
     140: ifne          296
     143: aload_0
     144: getfield      #27                 // Field quickCraftSlots:Ljava/util/Set;
     147: invokeinterface #221,  1          // InterfaceMethod java/util/Set.size:()I
     152: iconst_1
     153: if_icmpne     157
     156: return
     157: aload_2
     158: aload         10
     160: iconst_1
     161: invokestatic  #457                // Method net/minecraft/world/inventory/AbstractContainerMenu.canItemQuickReplace:(Lnet/minecraft/world/inventory/Slot;Lnet/minecraft/world/item/ItemStack;Z)Z
     164: ifeq          281
     167: aload_0
     168: getfield      #34                 // Field menu:Lnet/minecraft/world/inventory/AbstractContainerMenu;
     171: aload_2
     172: invokevirtual #461                // Method net/minecraft/world/inventory/AbstractContainerMenu.canDragTo:(Lnet/minecraft/world/inventory/Slot;)Z
     175: ifeq          281
     178: iconst_1
     179: istore        8
     181: aload         10
     183: invokevirtual #464                // Method net/minecraft/world/item/ItemStack.getMaxStackSize:()I
     186: aload_2
     187: aload         10
     189: invokevirtual #467                // Method net/minecraft/world/inventory/Slot.getMaxStackSize:(Lnet/minecraft/world/item/ItemStack;)I
     192: invokestatic  #470                // Method java/lang/Math.min:(II)I
     195: istore        12
     197: aload_2
     198: invokevirtual #332                // Method net/minecraft/world/inventory/Slot.getItem:()Lnet/minecraft/world/item/ItemStack;
     201: invokevirtual #191                // Method net/minecraft/world/item/ItemStack.isEmpty:()Z
     204: ifeq          211
     207: iconst_0
     208: goto          218
     211: aload_2
     212: invokevirtual #332                // Method net/minecraft/world/inventory/Slot.getItem:()Lnet/minecraft/world/item/ItemStack;
     215: invokevirtual #204                // Method net/minecraft/world/item/ItemStack.getCount:()I
     218: istore        13
     220: aload_0
     221: getfield      #27                 // Field quickCraftSlots:Ljava/util/Set;
     224: invokeinterface #221,  1          // InterfaceMethod java/util/Set.size:()I
     229: aload_0
     230: getfield      #476                // Field quickCraftingType:I
     233: aload         10
     235: invokestatic  #479                // Method net/minecraft/world/inventory/AbstractContainerMenu.getQuickCraftPlaceCount:(IILnet/minecraft/world/item/ItemStack;)I
     238: iload         13
     240: iadd
     241: istore        14
     243: iload         14
     245: iload         12
     247: if_icmple     269
     250: iload         12
     252: istore        14
     254: getstatic     #229                // Field net/minecraft/ChatFormatting.YELLOW:Lnet/minecraft/ChatFormatting;
     257: invokevirtual #483                // Method net/minecraft/ChatFormatting.toString:()Ljava/lang/String;
     260: iload         12
     262: invokedynamic #487,  0            // InvokeDynamic #3:makeConcatWithConstants:(Ljava/lang/String;I)Ljava/lang/String;
     267: astore        11
     269: aload         10
     271: iload         14
     273: invokevirtual #214                // Method net/minecraft/world/item/ItemStack.copyWithCount:(I)Lnet/minecraft/world/item/ItemStack;
     276: astore        7
     278: goto          296
     281: aload_0
     282: getfield      #27                 // Field quickCraftSlots:Ljava/util/Set;
     285: aload_2
     286: invokeinterface #490,  2          // InterfaceMethod java/util/Set.remove:(Ljava/lang/Object;)Z
     291: pop
     292: aload_0
     293: invokevirtual #493                // Method recalculateQuickCraftRemaining:()V
     296: aload         7
     298: invokevirtual #191                // Method net/minecraft/world/item/ItemStack.isEmpty:()Z
     301: ifeq          342
     304: aload_2
     305: invokevirtual #312                // Method net/minecraft/world/inventory/Slot.isActive:()Z
     308: ifeq          342
     311: aload_2
     312: invokevirtual #496                // Method net/minecraft/world/inventory/Slot.getNoItemIcon:()Lnet/minecraft/resources/Identifier;
     315: astore        12
     317: aload         12
     319: ifnull        342
     322: aload_1
     323: getstatic     #342                // Field net/minecraft/client/renderer/RenderPipelines.GUI_TEXTURED:Lcom/mojang/blaze3d/pipeline/RenderPipeline;
     326: aload         12
     328: iload         5
     330: iload         6
     332: bipush        16
     334: bipush        16
     336: invokevirtual #354                // Method net/minecraft/client/gui/GuiGraphicsExtractor.blitSprite:(Lcom/mojang/blaze3d/pipeline/RenderPipeline;Lnet/minecraft/resources/Identifier;IIII)V
     339: iconst_1
     340: istore        9
     342: iload         9
     344: ifne          383
     347: iload         8
     349: ifeq          373
     352: aload_1
     353: iload         5
     355: iload         6
     357: iload         5
     359: bipush        16
     361: iadd
     362: iload         6
     364: bipush        16
     366: iadd
     367: ldc_w         #500                // int -2130706433
     370: invokevirtual #501                // Method net/minecraft/client/gui/GuiGraphicsExtractor.fill:(IIIII)V
     373: aload_0
     374: aload_1
     375: aload         7
     377: aload_2
     378: aload         11
     380: invokevirtual #505                // Method renderSlotContents:(Lnet/minecraft/client/gui/GuiGraphicsExtractor;Lnet/minecraft/world/item/ItemStack;Lnet/minecraft/world/inventory/Slot;Ljava/lang/String;)V
     383: return

  protected void renderSlotContents(net.minecraft.client.gui.GuiGraphicsExtractor, net.minecraft.world.item.ItemStack, net.minecraft.world.inventory.Slot, java.lang.String);
    Code:
       0: aload_3
       1: getfield      #352                // Field net/minecraft/world/inventory/Slot.x:I
       4: istore        5
       6: aload_3
       7: getfield      #353                // Field net/minecraft/world/inventory/Slot.y:I
      10: istore        6
      12: aload_3
      13: getfield      #352                // Field net/minecraft/world/inventory/Slot.x:I
      16: aload_3
      17: getfield      #353                // Field net/minecraft/world/inventory/Slot.y:I
      20: aload_0
      21: getfield      #48                 // Field imageWidth:I
      24: imul
      25: iadd
      26: istore        7
      28: aload_3
      29: invokevirtual #509                // Method net/minecraft/world/inventory/Slot.isFake:()Z
      32: ifeq          49
      35: aload_1
      36: aload_2
      37: iload         5
      39: iload         6
      41: iload         7
      43: invokevirtual #512                // Method net/minecraft/client/gui/GuiGraphicsExtractor.fakeItem:(Lnet/minecraft/world/item/ItemStack;III)V
      46: goto          60
      49: aload_1
      50: aload_2
      51: iload         5
      53: iload         6
      55: iload         7
      57: invokevirtual #516                // Method net/minecraft/client/gui/GuiGraphicsExtractor.item:(Lnet/minecraft/world/item/ItemStack;III)V
      60: aload_2
      61: invokestatic  #423                // InterfaceMethod net/neoforged/neoforge/client/extensions/common/IClientItemExtensions.of:(Lnet/minecraft/world/item/ItemStack;)Lnet/neoforged/neoforge/client/extensions/common/IClientItemExtensions;
      64: aload_2
      65: getstatic     #429                // Field net/neoforged/neoforge/client/extensions/common/IClientItemExtensions$FontContext.ITEM_COUNT:Lnet/neoforged/neoforge/client/extensions/common/IClientItemExtensions$FontContext;
      68: invokeinterface #435,  3          // InterfaceMethod net/neoforged/neoforge/client/extensions/common/IClientItemExtensions.getFont:(Lnet/minecraft/world/item/ItemStack;Lnet/neoforged/neoforge/client/extensions/common/IClientItemExtensions$FontContext;)Lnet/minecraft/client/gui/Font;
      73: astore        8
      75: aload_1
      76: aload         8
      78: ifnull        86
      81: aload         8
      83: goto          90
      86: aload_0
      87: getfield      #365                // Field font:Lnet/minecraft/client/gui/Font;
      90: aload_2
      91: iload         5
      93: iload         6
      95: aload         4
      97: invokevirtual #439                // Method net/minecraft/client/gui/GuiGraphicsExtractor.itemDecorations:(Lnet/minecraft/client/gui/Font;Lnet/minecraft/world/item/ItemStack;IILjava/lang/String;)V
     100: return

  public boolean mouseClicked(net.minecraft.client.input.MouseButtonEvent, boolean);
    Code:
       0: aload_0
       1: aload_1
       2: iload_2
       3: invokespecial #523                // Method net/minecraft/client/gui/screens/Screen.mouseClicked:(Lnet/minecraft/client/input/MouseButtonEvent;Z)Z
       6: ifeq          11
       9: iconst_1
      10: ireturn
      11: getstatic     #527                // Field com/mojang/blaze3d/platform/InputConstants$Type.MOUSE:Lcom/mojang/blaze3d/platform/InputConstants$Type;
      14: aload_1
      15: invokevirtual #533                // Method net/minecraft/client/input/MouseButtonEvent.button:()I
      18: invokevirtual #538                // Method com/mojang/blaze3d/platform/InputConstants$Type.getOrCreate:(I)Lcom/mojang/blaze3d/platform/InputConstants$Key;
      21: astore_3
      22: aload_0
      23: getfield      #99                 // Field minecraft:Lnet/minecraft/client/Minecraft;
      26: getfield      #542                // Field net/minecraft/client/Minecraft.options:Lnet/minecraft/client/Options;
      29: getfield      #548                // Field net/minecraft/client/Options.keyPickItem:Lnet/minecraft/client/KeyMapping;
      32: aload_3
      33: invokevirtual #554                // Method net/minecraft/client/KeyMapping.isActiveAndMatches:(Lcom/mojang/blaze3d/platform/InputConstants$Key;)Z
      36: ifeq          56
      39: aload_0
      40: getfield      #99                 // Field minecraft:Lnet/minecraft/client/Minecraft;
      43: getfield      #560                // Field net/minecraft/client/Minecraft.player:Lnet/minecraft/client/player/LocalPlayer;
      46: invokevirtual #564                // Method net/minecraft/client/player/LocalPlayer.hasInfiniteMaterials:()Z
      49: ifeq          56
      52: iconst_1
      53: goto          57
      56: iconst_0
      57: istore        4
      59: aload_0
      60: aload_1
      61: invokevirtual #569                // Method net/minecraft/client/input/MouseButtonEvent.x:()D
      64: aload_1
      65: invokevirtual #572                // Method net/minecraft/client/input/MouseButtonEvent.y:()D
      68: invokevirtual #154                // Method getHoveredSlot:(DD)Lnet/minecraft/world/inventory/Slot;
      71: astore        5
      73: aload_0
      74: aload_0
      75: getfield      #574                // Field lastClickSlot:Lnet/minecraft/world/inventory/Slot;
      78: aload         5
      80: if_acmpne     91
      83: iload_2
      84: ifeq          91
      87: iconst_1
      88: goto          92
      91: iconst_0
      92: putfield      #577                // Field doubleclick:Z
      95: aload_0
      96: iconst_0
      97: putfield      #55                 // Field skipNextRelease:Z
     100: aload_1
     101: invokevirtual #533                // Method net/minecraft/client/input/MouseButtonEvent.button:()I
     104: ifeq          128
     107: aload_1
     108: invokevirtual #533                // Method net/minecraft/client/input/MouseButtonEvent.button:()I
     111: iconst_1
     112: if_icmpeq     128
     115: iload         4
     117: ifne          128
     120: aload_0
     121: aload_1
     122: invokevirtual #580                // Method checkHotbarMouseClicked:(Lnet/minecraft/client/input/MouseButtonEvent;)V
     125: goto          555
     128: aload_0
     129: getfield      #83                 // Field leftPos:I
     132: istore        6
     134: aload_0
     135: getfield      #89                 // Field topPos:I
     138: istore        7
     140: aload_0
     141: aload_1
     142: invokevirtual #569                // Method net/minecraft/client/input/MouseButtonEvent.x:()D
     145: aload_1
     146: invokevirtual #572                // Method net/minecraft/client/input/MouseButtonEvent.y:()D
     149: iload         6
     151: iload         7
     153: invokevirtual #584                // Method hasClickedOutside:(DDII)Z
     156: istore        8
     158: aload         5
     160: ifnull        166
     163: iconst_0
     164: istore        8
     166: iconst_m1
     167: istore        9
     169: aload         5
     171: ifnull        181
     174: aload         5
     176: getfield      #329                // Field net/minecraft/world/inventory/Slot.index:I
     179: istore        9
     181: iload         8
     183: ifeq          191
     186: sipush        -999
     189: istore        9
     191: aload_0
     192: getfield      #99                 // Field minecraft:Lnet/minecraft/client/Minecraft;
     195: getfield      #542                // Field net/minecraft/client/Minecraft.options:Lnet/minecraft/client/Options;
     198: invokevirtual #588                // Method net/minecraft/client/Options.touchscreen:()Lnet/minecraft/client/OptionInstance;
     201: invokevirtual #592                // Method net/minecraft/client/OptionInstance.get:()Ljava/lang/Object;
     204: checkcast     #405                // class java/lang/Boolean
     207: invokevirtual #413                // Method java/lang/Boolean.booleanValue:()Z
     210: ifeq          237
     213: iload         8
     215: ifeq          237
     218: aload_0
     219: getfield      #34                 // Field menu:Lnet/minecraft/world/inventory/AbstractContainerMenu;
     222: invokevirtual #195                // Method net/minecraft/world/inventory/AbstractContainerMenu.getCarried:()Lnet/minecraft/world/item/ItemStack;
     225: invokevirtual #191                // Method net/minecraft/world/item/ItemStack.isEmpty:()Z
     228: ifeq          237
     231: aload_0
     232: invokevirtual #596                // Method onClose:()V
     235: iconst_1
     236: ireturn
     237: iload         9
     239: iconst_m1
     240: if_icmpeq     555
     243: aload_0
     244: getfield      #99                 // Field minecraft:Lnet/minecraft/client/Minecraft;
     247: getfield      #542                // Field net/minecraft/client/Minecraft.options:Lnet/minecraft/client/Options;
     250: invokevirtual #588                // Method net/minecraft/client/Options.touchscreen:()Lnet/minecraft/client/OptionInstance;
     253: invokevirtual #592                // Method net/minecraft/client/OptionInstance.get:()Ljava/lang/Object;
     256: checkcast     #405                // class java/lang/Boolean
     259: invokevirtual #413                // Method java/lang/Boolean.booleanValue:()Z
     262: ifeq          319
     265: aload         5
     267: ifnull        311
     270: aload         5
     272: invokevirtual #319                // Method net/minecraft/world/inventory/Slot.hasItem:()Z
     275: ifeq          311
     278: aload_0
     279: aload         5
     281: putfield      #451                // Field clickedSlot:Lnet/minecraft/world/inventory/Slot;
     284: aload_0
     285: getstatic     #12                 // Field net/minecraft/world/item/ItemStack.EMPTY:Lnet/minecraft/world/item/ItemStack;
     288: putfield      #18                 // Field draggingItem:Lnet/minecraft/world/item/ItemStack;
     291: aload_0
     292: aload_1
     293: invokevirtual #533                // Method net/minecraft/client/input/MouseButtonEvent.button:()I
     296: iconst_1
     297: if_icmpne     304
     300: iconst_1
     301: goto          305
     304: iconst_0
     305: putfield      #201                // Field isSplittingStack:Z
     308: goto          555
     311: aload_0
     312: aconst_null
     313: putfield      #451                // Field clickedSlot:Lnet/minecraft/world/inventory/Slot;
     316: goto          555
     319: aload_0
     320: getfield      #218                // Field isQuickCrafting:Z
     323: ifne          555
     326: aload_0
     327: getfield      #34                 // Field menu:Lnet/minecraft/world/inventory/AbstractContainerMenu;
     330: invokevirtual #195                // Method net/minecraft/world/inventory/AbstractContainerMenu.getCarried:()Lnet/minecraft/world/item/ItemStack;
     333: invokevirtual #191                // Method net/minecraft/world/item/ItemStack.isEmpty:()Z
     336: ifeq          480
     339: aload_0
     340: getfield      #99                 // Field minecraft:Lnet/minecraft/client/Minecraft;
     343: getfield      #542                // Field net/minecraft/client/Minecraft.options:Lnet/minecraft/client/Options;
     346: getfield      #548                // Field net/minecraft/client/Options.keyPickItem:Lnet/minecraft/client/KeyMapping;
     349: aload_3
     350: invokevirtual #554                // Method net/minecraft/client/KeyMapping.isActiveAndMatches:(Lcom/mojang/blaze3d/platform/InputConstants$Key;)Z
     353: ifeq          374
     356: aload_0
     357: aload         5
     359: iload         9
     361: aload_1
     362: invokevirtual #533                // Method net/minecraft/client/input/MouseButtonEvent.button:()I
     365: getstatic     #599                // Field net/minecraft/world/inventory/ContainerInput.CLONE:Lnet/minecraft/world/inventory/ContainerInput;
     368: invokevirtual #605                // Method slotClicked:(Lnet/minecraft/world/inventory/Slot;IILnet/minecraft/world/inventory/ContainerInput;)V
     371: goto          472
     374: iload         9
     376: sipush        -999
     379: if_icmpeq     393
     382: aload_1
     383: invokevirtual #609                // Method net/minecraft/client/input/MouseButtonEvent.hasShiftDown:()Z
     386: ifeq          393
     389: iconst_1
     390: goto          394
     393: iconst_0
     394: istore        10
     396: getstatic     #612                // Field net/minecraft/world/inventory/ContainerInput.PICKUP:Lnet/minecraft/world/inventory/ContainerInput;
     399: astore        11
     401: iload         10
     403: ifeq          445
     406: aload_0
     407: aload         5
     409: ifnull        431
     412: aload         5
     414: invokevirtual #319                // Method net/minecraft/world/inventory/Slot.hasItem:()Z
     417: ifeq          431
     420: aload         5
     422: invokevirtual #332                // Method net/minecraft/world/inventory/Slot.getItem:()Lnet/minecraft/world/item/ItemStack;
     425: invokevirtual #615                // Method net/minecraft/world/item/ItemStack.copy:()Lnet/minecraft/world/item/ItemStack;
     428: goto          434
     431: getstatic     #12                 // Field net/minecraft/world/item/ItemStack.EMPTY:Lnet/minecraft/world/item/ItemStack;
     434: putfield      #31                 // Field lastQuickMoved:Lnet/minecraft/world/item/ItemStack;
     437: getstatic     #618                // Field net/minecraft/world/inventory/ContainerInput.QUICK_MOVE:Lnet/minecraft/world/inventory/ContainerInput;
     440: astore        11
     442: goto          458
     445: iload         9
     447: sipush        -999
     450: if_icmpne     458
     453: getstatic     #621                // Field net/minecraft/world/inventory/ContainerInput.THROW:Lnet/minecraft/world/inventory/ContainerInput;
     456: astore        11
     458: aload_0
     459: aload         5
     461: iload         9
     463: aload_1
     464: invokevirtual #533                // Method net/minecraft/client/input/MouseButtonEvent.button:()I
     467: aload         11
     469: invokevirtual #605                // Method slotClicked:(Lnet/minecraft/world/inventory/Slot;IILnet/minecraft/world/inventory/ContainerInput;)V
     472: aload_0
     473: iconst_1
     474: putfield      #55                 // Field skipNextRelease:Z
     477: goto          555
     480: aload_0
     481: iconst_1
     482: putfield      #218                // Field isQuickCrafting:Z
     485: aload_0
     486: aload_1
     487: invokevirtual #533                // Method net/minecraft/client/input/MouseButtonEvent.button:()I
     490: putfield      #624                // Field quickCraftingButton:I
     493: aload_0
     494: getfield      #27                 // Field quickCraftSlots:Ljava/util/Set;
     497: invokeinterface #627,  1          // InterfaceMethod java/util/Set.clear:()V
     502: aload_1
     503: invokevirtual #533                // Method net/minecraft/client/input/MouseButtonEvent.button:()I
     506: ifne          517
     509: aload_0
     510: iconst_0
     511: putfield      #476                // Field quickCraftingType:I
     514: goto          555
     517: aload_1
     518: invokevirtual #533                // Method net/minecraft/client/input/MouseButtonEvent.button:()I
     521: iconst_1
     522: if_icmpne     533
     525: aload_0
     526: iconst_1
     527: putfield      #476                // Field quickCraftingType:I
     530: goto          555
     533: aload_0
     534: getfield      #99                 // Field minecraft:Lnet/minecraft/client/Minecraft;
     537: getfield      #542                // Field net/minecraft/client/Minecraft.options:Lnet/minecraft/client/Options;
     540: getfield      #548                // Field net/minecraft/client/Options.keyPickItem:Lnet/minecraft/client/KeyMapping;
     543: aload_3
     544: invokevirtual #554                // Method net/minecraft/client/KeyMapping.isActiveAndMatches:(Lcom/mojang/blaze3d/platform/InputConstants$Key;)Z
     547: ifeq          555
     550: aload_0
     551: iconst_2
     552: putfield      #476                // Field quickCraftingType:I
     555: aload_0
     556: aload         5
     558: putfield      #574                // Field lastClickSlot:Lnet/minecraft/world/inventory/Slot;
     561: iconst_1
     562: ireturn

  protected boolean hasClickedOutside(double, double, int, int);
    Code:
       0: dload_1
       1: iload         5
       3: i2d
       4: dcmpg
       5: iflt          42
       8: dload_3
       9: iload         6
      11: i2d
      12: dcmpg
      13: iflt          42
      16: dload_1
      17: iload         5
      19: aload_0
      20: getfield      #48                 // Field imageWidth:I
      23: iadd
      24: i2d
      25: dcmpl
      26: ifge          42
      29: dload_3
      30: iload         6
      32: aload_0
      33: getfield      #52                 // Field imageHeight:I
      36: iadd
      37: i2d
      38: dcmpl
      39: iflt          46
      42: iconst_1
      43: goto          47
      46: iconst_0
      47: ireturn

  public boolean mouseDragged(net.minecraft.client.input.MouseButtonEvent, double, double);
    Code:
       0: aload_0
       1: aload_1
       2: invokevirtual #569                // Method net/minecraft/client/input/MouseButtonEvent.x:()D
       5: aload_1
       6: invokevirtual #572                // Method net/minecraft/client/input/MouseButtonEvent.y:()D
       9: invokevirtual #154                // Method getHoveredSlot:(DD)Lnet/minecraft/world/inventory/Slot;
      12: astore        6
      14: aload_0
      15: getfield      #34                 // Field menu:Lnet/minecraft/world/inventory/AbstractContainerMenu;
      18: invokevirtual #195                // Method net/minecraft/world/inventory/AbstractContainerMenu.getCarried:()Lnet/minecraft/world/item/ItemStack;
      21: astore        7
      23: aload_0
      24: getfield      #451                // Field clickedSlot:Lnet/minecraft/world/inventory/Slot;
      27: ifnull        261
      30: aload_0
      31: getfield      #99                 // Field minecraft:Lnet/minecraft/client/Minecraft;
      34: getfield      #542                // Field net/minecraft/client/Minecraft.options:Lnet/minecraft/client/Options;
      37: invokevirtual #588                // Method net/minecraft/client/Options.touchscreen:()Lnet/minecraft/client/OptionInstance;
      40: invokevirtual #592                // Method net/minecraft/client/OptionInstance.get:()Ljava/lang/Object;
      43: checkcast     #405                // class java/lang/Boolean
      46: invokevirtual #413                // Method java/lang/Boolean.booleanValue:()Z
      49: ifeq          261
      52: aload_1
      53: invokevirtual #533                // Method net/minecraft/client/input/MouseButtonEvent.button:()I
      56: ifeq          67
      59: aload_1
      60: invokevirtual #533                // Method net/minecraft/client/input/MouseButtonEvent.button:()I
      63: iconst_1
      64: if_icmpne     259
      67: aload_0
      68: getfield      #18                 // Field draggingItem:Lnet/minecraft/world/item/ItemStack;
      71: invokevirtual #191                // Method net/minecraft/world/item/ItemStack.isEmpty:()Z
      74: ifeq          116
      77: aload         6
      79: aload_0
      80: getfield      #451                // Field clickedSlot:Lnet/minecraft/world/inventory/Slot;
      83: if_acmpeq     259
      86: aload_0
      87: getfield      #451                // Field clickedSlot:Lnet/minecraft/world/inventory/Slot;
      90: invokevirtual #332                // Method net/minecraft/world/inventory/Slot.getItem:()Lnet/minecraft/world/item/ItemStack;
      93: invokevirtual #191                // Method net/minecraft/world/item/ItemStack.isEmpty:()Z
      96: ifne          259
      99: aload_0
     100: aload_0
     101: getfield      #451                // Field clickedSlot:Lnet/minecraft/world/inventory/Slot;
     104: invokevirtual #332                // Method net/minecraft/world/inventory/Slot.getItem:()Lnet/minecraft/world/item/ItemStack;
     107: invokevirtual #615                // Method net/minecraft/world/item/ItemStack.copy:()Lnet/minecraft/world/item/ItemStack;
     110: putfield      #18                 // Field draggingItem:Lnet/minecraft/world/item/ItemStack;
     113: goto          259
     116: aload_0
     117: getfield      #18                 // Field draggingItem:Lnet/minecraft/world/item/ItemStack;
     120: invokevirtual #204                // Method net/minecraft/world/item/ItemStack.getCount:()I
     123: iconst_1
     124: if_icmple     259
     127: aload         6
     129: ifnull        259
     132: aload         6
     134: aload_0
     135: getfield      #18                 // Field draggingItem:Lnet/minecraft/world/item/ItemStack;
     138: iconst_0
     139: invokestatic  #457                // Method net/minecraft/world/inventory/AbstractContainerMenu.canItemQuickReplace:(Lnet/minecraft/world/inventory/Slot;Lnet/minecraft/world/item/ItemStack;Z)Z
     142: ifeq          259
     145: invokestatic  #256                // Method net/minecraft/util/Util.getMillis:()J
     148: lstore        8
     150: aload_0
     151: getfield      #642                // Field quickdropSlot:Lnet/minecraft/world/inventory/Slot;
     154: aload         6
     156: if_acmpne     247
     159: lload         8
     161: aload_0
     162: getfield      #645                // Field quickdropTime:J
     165: lsub
     166: ldc2_w        #648                // long 500l
     169: lcmp
     170: ifle          259
     173: aload_0
     174: aload_0
     175: getfield      #451                // Field clickedSlot:Lnet/minecraft/world/inventory/Slot;
     178: aload_0
     179: getfield      #451                // Field clickedSlot:Lnet/minecraft/world/inventory/Slot;
     182: getfield      #329                // Field net/minecraft/world/inventory/Slot.index:I
     185: iconst_0
     186: getstatic     #612                // Field net/minecraft/world/inventory/ContainerInput.PICKUP:Lnet/minecraft/world/inventory/ContainerInput;
     189: invokevirtual #605                // Method slotClicked:(Lnet/minecraft/world/inventory/Slot;IILnet/minecraft/world/inventory/ContainerInput;)V
     192: aload_0
     193: aload         6
     195: aload         6
     197: getfield      #329                // Field net/minecraft/world/inventory/Slot.index:I
     200: iconst_1
     201: getstatic     #612                // Field net/minecraft/world/inventory/ContainerInput.PICKUP:Lnet/minecraft/world/inventory/ContainerInput;
     204: invokevirtual #605                // Method slotClicked:(Lnet/minecraft/world/inventory/Slot;IILnet/minecraft/world/inventory/ContainerInput;)V
     207: aload_0
     208: aload_0
     209: getfield      #451                // Field clickedSlot:Lnet/minecraft/world/inventory/Slot;
     212: aload_0
     213: getfield      #451                // Field clickedSlot:Lnet/minecraft/world/inventory/Slot;
     216: getfield      #329                // Field net/minecraft/world/inventory/Slot.index:I
     219: iconst_0
     220: getstatic     #612                // Field net/minecraft/world/inventory/ContainerInput.PICKUP:Lnet/minecraft/world/inventory/ContainerInput;
     223: invokevirtual #605                // Method slotClicked:(Lnet/minecraft/world/inventory/Slot;IILnet/minecraft/world/inventory/ContainerInput;)V
     226: aload_0
     227: lload         8
     229: ldc2_w        #650                // long 750l
     232: ladd
     233: putfield      #645                // Field quickdropTime:J
     236: aload_0
     237: getfield      #18                 // Field draggingItem:Lnet/minecraft/world/item/ItemStack;
     240: iconst_1
     241: invokevirtual #652                // Method net/minecraft/world/item/ItemStack.shrink:(I)V
     244: goto          259
     247: aload_0
     248: aload         6
     250: putfield      #642                // Field quickdropSlot:Lnet/minecraft/world/inventory/Slot;
     253: aload_0
     254: lload         8
     256: putfield      #645                // Field quickdropTime:J
     259: iconst_1
     260: ireturn
     261: aload         6
     263: ifnull        297
     266: aload_0
     267: aload         6
     269: aload         7
     271: invokevirtual #656                // Method shouldAddSlotToQuickCraft:(Lnet/minecraft/world/inventory/Slot;Lnet/minecraft/world/item/ItemStack;)Z
     274: ifeq          297
     277: aload_0
     278: getfield      #27                 // Field quickCraftSlots:Ljava/util/Set;
     281: aload         6
     283: invokeinterface #660,  2          // InterfaceMethod java/util/Set.add:(Ljava/lang/Object;)Z
     288: ifeq          297
     291: aload_0
     292: invokevirtual #493                // Method recalculateQuickCraftRemaining:()V
     295: iconst_1
     296: ireturn
     297: aload         6
     299: ifnonnull     326
     302: aload_0
     303: getfield      #34                 // Field menu:Lnet/minecraft/world/inventory/AbstractContainerMenu;
     306: invokevirtual #195                // Method net/minecraft/world/inventory/AbstractContainerMenu.getCarried:()Lnet/minecraft/world/item/ItemStack;
     309: invokevirtual #191                // Method net/minecraft/world/item/ItemStack.isEmpty:()Z
     312: ifeq          326
     315: aload_0
     316: aload_1
     317: dload_2
     318: dload         4
     320: invokespecial #661                // Method net/minecraft/client/gui/screens/Screen.mouseDragged:(Lnet/minecraft/client/input/MouseButtonEvent;DD)Z
     323: goto          327
     326: iconst_1
     327: ireturn

  public boolean mouseReleased(net.minecraft.client.input.MouseButtonEvent);
    Code:
       0: aload_0
       1: aload_1
       2: invokespecial #665                // Method net/minecraft/client/gui/screens/Screen.mouseReleased:(Lnet/minecraft/client/input/MouseButtonEvent;)Z
       5: pop
       6: aload_0
       7: aload_1
       8: invokevirtual #569                // Method net/minecraft/client/input/MouseButtonEvent.x:()D
      11: aload_1
      12: invokevirtual #572                // Method net/minecraft/client/input/MouseButtonEvent.y:()D
      15: invokevirtual #154                // Method getHoveredSlot:(DD)Lnet/minecraft/world/inventory/Slot;
      18: astore_2
      19: aload_0
      20: getfield      #83                 // Field leftPos:I
      23: istore_3
      24: aload_0
      25: getfield      #89                 // Field topPos:I
      28: istore        4
      30: aload_0
      31: aload_1
      32: invokevirtual #569                // Method net/minecraft/client/input/MouseButtonEvent.x:()D
      35: aload_1
      36: invokevirtual #572                // Method net/minecraft/client/input/MouseButtonEvent.y:()D
      39: iload_3
      40: iload         4
      42: invokevirtual #584                // Method hasClickedOutside:(DDII)Z
      45: istore        5
      47: aload_2
      48: ifnull        54
      51: iconst_0
      52: istore        5
      54: getstatic     #527                // Field com/mojang/blaze3d/platform/InputConstants$Type.MOUSE:Lcom/mojang/blaze3d/platform/InputConstants$Type;
      57: aload_1
      58: invokevirtual #533                // Method net/minecraft/client/input/MouseButtonEvent.button:()I
      61: invokevirtual #538                // Method com/mojang/blaze3d/platform/InputConstants$Type.getOrCreate:(I)Lcom/mojang/blaze3d/platform/InputConstants$Key;
      64: astore        6
      66: iconst_m1
      67: istore        7
      69: aload_2
      70: ifnull        79
      73: aload_2
      74: getfield      #329                // Field net/minecraft/world/inventory/Slot.index:I
      77: istore        7
      79: iload         5
      81: ifeq          89
      84: sipush        -999
      87: istore        7
      89: aload_0
      90: getfield      #577                // Field doubleclick:Z
      93: ifeq          268
      96: aload_2
      97: ifnull        268
     100: aload_1
     101: invokevirtual #533                // Method net/minecraft/client/input/MouseButtonEvent.button:()I
     104: ifne          268
     107: aload_0
     108: getfield      #34                 // Field menu:Lnet/minecraft/world/inventory/AbstractContainerMenu;
     111: getstatic     #12                 // Field net/minecraft/world/item/ItemStack.EMPTY:Lnet/minecraft/world/item/ItemStack;
     114: aload_2
     115: invokevirtual #668                // Method net/minecraft/world/inventory/AbstractContainerMenu.canTakeItemForPickAll:(Lnet/minecraft/world/item/ItemStack;Lnet/minecraft/world/inventory/Slot;)Z
     118: ifeq          268
     121: aload_1
     122: invokevirtual #609                // Method net/minecraft/client/input/MouseButtonEvent.hasShiftDown:()Z
     125: ifeq          246
     128: aload_0
     129: getfield      #31                 // Field lastQuickMoved:Lnet/minecraft/world/item/ItemStack;
     132: invokevirtual #191                // Method net/minecraft/world/item/ItemStack.isEmpty:()Z
     135: ifne          260
     138: aload_0
     139: getfield      #34                 // Field menu:Lnet/minecraft/world/inventory/AbstractContainerMenu;
     142: getfield      #291                // Field net/minecraft/world/inventory/AbstractContainerMenu.slots:Lnet/minecraft/core/NonNullList;
     145: invokevirtual #295                // Method net/minecraft/core/NonNullList.iterator:()Ljava/util/Iterator;
     148: astore        8
     150: aload         8
     152: invokeinterface #301,  1          // InterfaceMethod java/util/Iterator.hasNext:()Z
     157: ifeq          243
     160: aload         8
     162: invokeinterface #306,  1          // InterfaceMethod java/util/Iterator.next:()Ljava/lang/Object;
     167: checkcast     #310                // class net/minecraft/world/inventory/Slot
     170: astore        9
     172: aload         9
     174: ifnull        240
     177: aload         9
     179: aload_0
     180: getfield      #99                 // Field minecraft:Lnet/minecraft/client/Minecraft;
     183: getfield      #560                // Field net/minecraft/client/Minecraft.player:Lnet/minecraft/client/player/LocalPlayer;
     186: invokevirtual #672                // Method net/minecraft/world/inventory/Slot.mayPickup:(Lnet/minecraft/world/entity/player/Player;)Z
     189: ifeq          240
     192: aload         9
     194: invokevirtual #319                // Method net/minecraft/world/inventory/Slot.hasItem:()Z
     197: ifeq          240
     200: aload         9
     202: aload_2
     203: invokevirtual #676                // Method net/minecraft/world/inventory/Slot.isSameInventory:(Lnet/minecraft/world/inventory/Slot;)Z
     206: ifeq          240
     209: aload         9
     211: aload_0
     212: getfield      #31                 // Field lastQuickMoved:Lnet/minecraft/world/item/ItemStack;
     215: iconst_1
     216: invokestatic  #457                // Method net/minecraft/world/inventory/AbstractContainerMenu.canItemQuickReplace:(Lnet/minecraft/world/inventory/Slot;Lnet/minecraft/world/item/ItemStack;Z)Z
     219: ifeq          240
     222: aload_0
     223: aload         9
     225: aload         9
     227: getfield      #329                // Field net/minecraft/world/inventory/Slot.index:I
     230: aload_1
     231: invokevirtual #533                // Method net/minecraft/client/input/MouseButtonEvent.button:()I
     234: getstatic     #618                // Field net/minecraft/world/inventory/ContainerInput.QUICK_MOVE:Lnet/minecraft/world/inventory/ContainerInput;
     237: invokevirtual #605                // Method slotClicked:(Lnet/minecraft/world/inventory/Slot;IILnet/minecraft/world/inventory/ContainerInput;)V
     240: goto          150
     243: goto          260
     246: aload_0
     247: aload_2
     248: iload         7
     250: aload_1
     251: invokevirtual #533                // Method net/minecraft/client/input/MouseButtonEvent.button:()I
     254: getstatic     #679                // Field net/minecraft/world/inventory/ContainerInput.PICKUP_ALL:Lnet/minecraft/world/inventory/ContainerInput;
     257: invokevirtual #605                // Method slotClicked:(Lnet/minecraft/world/inventory/Slot;IILnet/minecraft/world/inventory/ContainerInput;)V
     260: aload_0
     261: iconst_0
     262: putfield      #577                // Field doubleclick:Z
     265: goto          798
     268: aload_0
     269: getfield      #218                // Field isQuickCrafting:Z
     272: ifeq          307
     275: aload_0
     276: getfield      #624                // Field quickCraftingButton:I
     279: aload_1
     280: invokevirtual #533                // Method net/minecraft/client/input/MouseButtonEvent.button:()I
     283: if_icmpeq     307
     286: aload_0
     287: iconst_0
     288: putfield      #218                // Field isQuickCrafting:Z
     291: aload_0
     292: getfield      #27                 // Field quickCraftSlots:Ljava/util/Set;
     295: invokeinterface #627,  1          // InterfaceMethod java/util/Set.clear:()V
     300: aload_0
     301: iconst_1
     302: putfield      #55                 // Field skipNextRelease:Z
     305: iconst_1
     306: ireturn
     307: aload_0
     308: getfield      #55                 // Field skipNextRelease:Z
     311: ifeq          321
     314: aload_0
     315: iconst_0
     316: putfield      #55                 // Field skipNextRelease:Z
     319: iconst_1
     320: ireturn
     321: aload_0
     322: getfield      #451                // Field clickedSlot:Lnet/minecraft/world/inventory/Slot;
     325: ifnull        644
     328: aload_0
     329: getfield      #99                 // Field minecraft:Lnet/minecraft/client/Minecraft;
     332: getfield      #542                // Field net/minecraft/client/Minecraft.options:Lnet/minecraft/client/Options;
     335: invokevirtual #588                // Method net/minecraft/client/Options.touchscreen:()Lnet/minecraft/client/OptionInstance;
     338: invokevirtual #592                // Method net/minecraft/client/OptionInstance.get:()Ljava/lang/Object;
     341: checkcast     #405                // class java/lang/Boolean
     344: invokevirtual #413                // Method java/lang/Boolean.booleanValue:()Z
     347: ifeq          644
     350: aload_1
     351: invokevirtual #533                // Method net/minecraft/client/input/MouseButtonEvent.button:()I
     354: ifeq          365
     357: aload_1
     358: invokevirtual #533                // Method net/minecraft/client/input/MouseButtonEvent.button:()I
     361: iconst_1
     362: if_icmpne     798
     365: aload_0
     366: getfield      #18                 // Field draggingItem:Lnet/minecraft/world/item/ItemStack;
     369: invokevirtual #191                // Method net/minecraft/world/item/ItemStack.isEmpty:()Z
     372: ifeq          394
     375: aload_2
     376: aload_0
     377: getfield      #451                // Field clickedSlot:Lnet/minecraft/world/inventory/Slot;
     380: if_acmpeq     394
     383: aload_0
     384: aload_0
     385: getfield      #451                // Field clickedSlot:Lnet/minecraft/world/inventory/Slot;
     388: invokevirtual #332                // Method net/minecraft/world/inventory/Slot.getItem:()Lnet/minecraft/world/item/ItemStack;
     391: putfield      #18                 // Field draggingItem:Lnet/minecraft/world/item/ItemStack;
     394: aload_2
     395: aload_0
     396: getfield      #18                 // Field draggingItem:Lnet/minecraft/world/item/ItemStack;
     399: iconst_0
     400: invokestatic  #457                // Method net/minecraft/world/inventory/AbstractContainerMenu.canItemQuickReplace:(Lnet/minecraft/world/inventory/Slot;Lnet/minecraft/world/item/ItemStack;Z)Z
     403: istore        8
     405: iload         7
     407: iconst_m1
     408: if_icmpeq     566
     411: aload_0
     412: getfield      #18                 // Field draggingItem:Lnet/minecraft/world/item/ItemStack;
     415: invokevirtual #191                // Method net/minecraft/world/item/ItemStack.isEmpty:()Z
     418: ifne          566
     421: iload         8
     423: ifeq          566
     426: aload_0
     427: aload_0
     428: getfield      #451                // Field clickedSlot:Lnet/minecraft/world/inventory/Slot;
     431: aload_0
     432: getfield      #451                // Field clickedSlot:Lnet/minecraft/world/inventory/Slot;
     435: getfield      #329                // Field net/minecraft/world/inventory/Slot.index:I
     438: aload_1
     439: invokevirtual #533                // Method net/minecraft/client/input/MouseButtonEvent.button:()I
     442: getstatic     #612                // Field net/minecraft/world/inventory/ContainerInput.PICKUP:Lnet/minecraft/world/inventory/ContainerInput;
     445: invokevirtual #605                // Method slotClicked:(Lnet/minecraft/world/inventory/Slot;IILnet/minecraft/world/inventory/ContainerInput;)V
     448: aload_0
     449: aload_2
     450: iload         7
     452: iconst_0
     453: getstatic     #612                // Field net/minecraft/world/inventory/ContainerInput.PICKUP:Lnet/minecraft/world/inventory/ContainerInput;
     456: invokevirtual #605                // Method slotClicked:(Lnet/minecraft/world/inventory/Slot;IILnet/minecraft/world/inventory/ContainerInput;)V
     459: aload_0
     460: getfield      #34                 // Field menu:Lnet/minecraft/world/inventory/AbstractContainerMenu;
     463: invokevirtual #195                // Method net/minecraft/world/inventory/AbstractContainerMenu.getCarried:()Lnet/minecraft/world/item/ItemStack;
     466: invokevirtual #191                // Method net/minecraft/world/item/ItemStack.isEmpty:()Z
     469: ifeq          480
     472: aload_0
     473: aconst_null
     474: putfield      #252                // Field snapbackData:Lnet/minecraft/client/gui/screens/inventory/AbstractContainerScreen$SnapbackData;
     477: goto          637
     480: aload_0
     481: aload_0
     482: getfield      #451                // Field clickedSlot:Lnet/minecraft/world/inventory/Slot;
     485: aload_0
     486: getfield      #451                // Field clickedSlot:Lnet/minecraft/world/inventory/Slot;
     489: getfield      #329                // Field net/minecraft/world/inventory/Slot.index:I
     492: aload_1
     493: invokevirtual #533                // Method net/minecraft/client/input/MouseButtonEvent.button:()I
     496: getstatic     #612                // Field net/minecraft/world/inventory/ContainerInput.PICKUP:Lnet/minecraft/world/inventory/ContainerInput;
     499: invokevirtual #605                // Method slotClicked:(Lnet/minecraft/world/inventory/Slot;IILnet/minecraft/world/inventory/ContainerInput;)V
     502: aload_0
     503: new           #263                // class net/minecraft/client/gui/screens/inventory/AbstractContainerScreen$SnapbackData
     506: dup
     507: aload_0
     508: getfield      #18                 // Field draggingItem:Lnet/minecraft/world/item/ItemStack;
     511: new           #278                // class org/joml/Vector2i
     514: dup
     515: aload_1
     516: invokevirtual #569                // Method net/minecraft/client/input/MouseButtonEvent.x:()D
     519: d2i
     520: aload_1
     521: invokevirtual #572                // Method net/minecraft/client/input/MouseButtonEvent.y:()D
     524: d2i
     525: invokespecial #682                // Method org/joml/Vector2i."<init>":(II)V
     528: new           #278                // class org/joml/Vector2i
     531: dup
     532: aload_0
     533: getfield      #451                // Field clickedSlot:Lnet/minecraft/world/inventory/Slot;
     536: getfield      #352                // Field net/minecraft/world/inventory/Slot.x:I
     539: iload_3
     540: iadd
     541: aload_0
     542: getfield      #451                // Field clickedSlot:Lnet/minecraft/world/inventory/Slot;
     545: getfield      #353                // Field net/minecraft/world/inventory/Slot.y:I
     548: iload         4
     550: iadd
     551: invokespecial #682                // Method org/joml/Vector2i."<init>":(II)V
     554: invokestatic  #256                // Method net/minecraft/util/Util.getMillis:()J
     557: invokespecial #685                // Method net/minecraft/client/gui/screens/inventory/AbstractContainerScreen$SnapbackData."<init>":(Lnet/minecraft/world/item/ItemStack;Lorg/joml/Vector2i;Lorg/joml/Vector2i;J)V
     560: putfield      #252                // Field snapbackData:Lnet/minecraft/client/gui/screens/inventory/AbstractContainerScreen$SnapbackData;
     563: goto          637
     566: aload_0
     567: getfield      #18                 // Field draggingItem:Lnet/minecraft/world/item/ItemStack;
     570: invokevirtual #191                // Method net/minecraft/world/item/ItemStack.isEmpty:()Z
     573: ifne          637
     576: aload_0
     577: new           #263                // class net/minecraft/client/gui/screens/inventory/AbstractContainerScreen$SnapbackData
     580: dup
     581: aload_0
     582: getfield      #18                 // Field draggingItem:Lnet/minecraft/world/item/ItemStack;
     585: new           #278                // class org/joml/Vector2i
     588: dup
     589: aload_1
     590: invokevirtual #569                // Method net/minecraft/client/input/MouseButtonEvent.x:()D
     593: d2i
     594: aload_1
     595: invokevirtual #572                // Method net/minecraft/client/input/MouseButtonEvent.y:()D
     598: d2i
     599: invokespecial #682                // Method org/joml/Vector2i."<init>":(II)V
     602: new           #278                // class org/joml/Vector2i
     605: dup
     606: aload_0
     607: getfield      #451                // Field clickedSlot:Lnet/minecraft/world/inventory/Slot;
     610: getfield      #352                // Field net/minecraft/world/inventory/Slot.x:I
     613: iload_3
     614: iadd
     615: aload_0
     616: getfield      #451                // Field clickedSlot:Lnet/minecraft/world/inventory/Slot;
     619: getfield      #353                // Field net/minecraft/world/inventory/Slot.y:I
     622: iload         4
     624: iadd
     625: invokespecial #682                // Method org/joml/Vector2i."<init>":(II)V
     628: invokestatic  #256                // Method net/minecraft/util/Util.getMillis:()J
     631: invokespecial #685                // Method net/minecraft/client/gui/screens/inventory/AbstractContainerScreen$SnapbackData."<init>":(Lnet/minecraft/world/item/ItemStack;Lorg/joml/Vector2i;Lorg/joml/Vector2i;J)V
     634: putfield      #252                // Field snapbackData:Lnet/minecraft/client/gui/screens/inventory/AbstractContainerScreen$SnapbackData;
     637: aload_0
     638: invokevirtual #688                // Method clearDraggingState:()V
     641: goto          798
     644: aload_0
     645: getfield      #218                // Field isQuickCrafting:Z
     648: ifeq          670
     651: aload_0
     652: getfield      #27                 // Field quickCraftSlots:Ljava/util/Set;
     655: invokeinterface #691,  1          // InterfaceMethod java/util/Set.isEmpty:()Z
     660: ifne          670
     663: aload_0
     664: invokevirtual #692                // Method quickCraftToSlots:()V
     667: goto          798
     670: aload_0
     671: getfield      #34                 // Field menu:Lnet/minecraft/world/inventory/AbstractContainerMenu;
     674: invokevirtual #195                // Method net/minecraft/world/inventory/AbstractContainerMenu.getCarried:()Lnet/minecraft/world/item/ItemStack;
     677: invokevirtual #191                // Method net/minecraft/world/item/ItemStack.isEmpty:()Z
     680: ifne          798
     683: aload_0
     684: getfield      #99                 // Field minecraft:Lnet/minecraft/client/Minecraft;
     687: getfield      #542                // Field net/minecraft/client/Minecraft.options:Lnet/minecraft/client/Options;
     690: getfield      #548                // Field net/minecraft/client/Options.keyPickItem:Lnet/minecraft/client/KeyMapping;
     693: aload         6
     695: invokevirtual #554                // Method net/minecraft/client/KeyMapping.isActiveAndMatches:(Lcom/mojang/blaze3d/platform/InputConstants$Key;)Z
     698: ifeq          718
     701: aload_0
     702: aload_2
     703: iload         7
     705: aload_1
     706: invokevirtual #533                // Method net/minecraft/client/input/MouseButtonEvent.button:()I
     709: getstatic     #599                // Field net/minecraft/world/inventory/ContainerInput.CLONE:Lnet/minecraft/world/inventory/ContainerInput;
     712: invokevirtual #605                // Method slotClicked:(Lnet/minecraft/world/inventory/Slot;IILnet/minecraft/world/inventory/ContainerInput;)V
     715: goto          798
     718: iload         7
     720: sipush        -999
     723: if_icmpeq     737
     726: aload_1
     727: invokevirtual #609                // Method net/minecraft/client/input/MouseButtonEvent.hasShiftDown:()Z
     730: ifeq          737
     733: iconst_1
     734: goto          738
     737: iconst_0
     738: istore        8
     740: iload         8
     742: ifeq          773
     745: aload_0
     746: aload_2
     747: ifnull        767
     750: aload_2
     751: invokevirtual #319                // Method net/minecraft/world/inventory/Slot.hasItem:()Z
     754: ifeq          767
     757: aload_2
     758: invokevirtual #332                // Method net/minecraft/world/inventory/Slot.getItem:()Lnet/minecraft/world/item/ItemStack;
     761: invokevirtual #615                // Method net/minecraft/world/item/ItemStack.copy:()Lnet/minecraft/world/item/ItemStack;
     764: goto          770
     767: getstatic     #12                 // Field net/minecraft/world/item/ItemStack.EMPTY:Lnet/minecraft/world/item/ItemStack;
     770: putfield      #31                 // Field lastQuickMoved:Lnet/minecraft/world/item/ItemStack;
     773: aload_0
     774: aload_2
     775: iload         7
     777: aload_1
     778: invokevirtual #533                // Method net/minecraft/client/input/MouseButtonEvent.button:()I
     781: iload         8
     783: ifeq          792
     786: getstatic     #618                // Field net/minecraft/world/inventory/ContainerInput.QUICK_MOVE:Lnet/minecraft/world/inventory/ContainerInput;
     789: goto          795
     792: getstatic     #612                // Field net/minecraft/world/inventory/ContainerInput.PICKUP:Lnet/minecraft/world/inventory/ContainerInput;
     795: invokevirtual #605                // Method slotClicked:(Lnet/minecraft/world/inventory/Slot;IILnet/minecraft/world/inventory/ContainerInput;)V
     798: aload_0
     799: iconst_0
     800: putfield      #218                // Field isQuickCrafting:Z
     803: aload_0
     804: aload_1
     805: invokespecial #665                // Method net/minecraft/client/gui/screens/Screen.mouseReleased:(Lnet/minecraft/client/input/MouseButtonEvent;)Z
     808: ireturn

  public void clearDraggingState();
    Code:
       0: aload_0
       1: getstatic     #12                 // Field net/minecraft/world/item/ItemStack.EMPTY:Lnet/minecraft/world/item/ItemStack;
       4: putfield      #18                 // Field draggingItem:Lnet/minecraft/world/item/ItemStack;
       7: aload_0
       8: aconst_null
       9: putfield      #451                // Field clickedSlot:Lnet/minecraft/world/inventory/Slot;
      12: return

  protected boolean isHovering(int, int, int, int, double, double);
    Code:
       0: aload_0
       1: getfield      #83                 // Field leftPos:I
       4: istore        9
       6: aload_0
       7: getfield      #89                 // Field topPos:I
      10: istore        10
      12: dload         5
      14: iload         9
      16: i2d
      17: dsub
      18: dstore        5
      20: dload         7
      22: iload         10
      24: i2d
      25: dsub
      26: dstore        7
      28: dload         5
      30: iload_1
      31: iconst_1
      32: isub
      33: i2d
      34: dcmpl
      35: iflt          77
      38: dload         5
      40: iload_1
      41: iload_3
      42: iadd
      43: iconst_1
      44: iadd
      45: i2d
      46: dcmpg
      47: ifge          77
      50: dload         7
      52: iload_2
      53: iconst_1
      54: isub
      55: i2d
      56: dcmpl
      57: iflt          77
      60: dload         7
      62: iload_2
      63: iload         4
      65: iadd
      66: iconst_1
      67: iadd
      68: i2d
      69: dcmpg
      70: ifge          77
      73: iconst_1
      74: goto          78
      77: iconst_0
      78: ireturn

  protected void slotClicked(net.minecraft.world.inventory.Slot, int, int, net.minecraft.world.inventory.ContainerInput);
    Code:
       0: aload_1
       1: ifnull        9
       4: aload_1
       5: getfield      #329                // Field net/minecraft/world/inventory/Slot.index:I
       8: istore_2
       9: aload_0
      10: aload_1
      11: aload         4
      13: invokevirtual #699                // Method onMouseClickAction:(Lnet/minecraft/world/inventory/Slot;Lnet/minecraft/world/inventory/ContainerInput;)V
      16: aload_0
      17: getfield      #99                 // Field minecraft:Lnet/minecraft/client/Minecraft;
      20: getfield      #703                // Field net/minecraft/client/Minecraft.gameMode:Lnet/minecraft/client/multiplayer/MultiPlayerGameMode;
      23: aload_0
      24: getfield      #34                 // Field menu:Lnet/minecraft/world/inventory/AbstractContainerMenu;
      27: getfield      #707                // Field net/minecraft/world/inventory/AbstractContainerMenu.containerId:I
      30: iload_2
      31: iload_3
      32: aload         4
      34: aload_0
      35: getfield      #99                 // Field minecraft:Lnet/minecraft/client/Minecraft;
      38: getfield      #560                // Field net/minecraft/client/Minecraft.player:Lnet/minecraft/client/player/LocalPlayer;
      41: invokevirtual #710                // Method net/minecraft/client/multiplayer/MultiPlayerGameMode.handleContainerInput:(IIILnet/minecraft/world/inventory/ContainerInput;Lnet/minecraft/world/entity/player/Player;)V
      44: return

  void onMouseClickAction(net.minecraft.world.inventory.Slot, net.minecraft.world.inventory.ContainerInput);
    Code:
       0: aload_1
       1: ifnull        64
       4: aload_1
       5: invokevirtual #319                // Method net/minecraft/world/inventory/Slot.hasItem:()Z
       8: ifeq          64
      11: aload_0
      12: getfield      #76                 // Field itemSlotMouseActions:Ljava/util/List;
      15: invokeinterface #322,  1          // InterfaceMethod java/util/List.iterator:()Ljava/util/Iterator;
      20: astore_3
      21: aload_3
      22: invokeinterface #301,  1          // InterfaceMethod java/util/Iterator.hasNext:()Z
      27: ifeq          64
      30: aload_3
      31: invokeinterface #306,  1          // InterfaceMethod java/util/Iterator.next:()Ljava/lang/Object;
      36: checkcast     #323                // class net/minecraft/client/gui/ItemSlotMouseAction
      39: astore        4
      41: aload         4
      43: aload_1
      44: invokeinterface #325,  2          // InterfaceMethod net/minecraft/client/gui/ItemSlotMouseAction.matches:(Lnet/minecraft/world/inventory/Slot;)Z
      49: ifeq          61
      52: aload         4
      54: aload_1
      55: aload_2
      56: invokeinterface #716,  3          // InterfaceMethod net/minecraft/client/gui/ItemSlotMouseAction.onSlotClicked:(Lnet/minecraft/world/inventory/Slot;Lnet/minecraft/world/inventory/ContainerInput;)V
      61: goto          21
      64: return

  protected void handleSlotStateChanged(int, int, boolean);
    Code:
       0: aload_0
       1: getfield      #99                 // Field minecraft:Lnet/minecraft/client/Minecraft;
       4: getfield      #703                // Field net/minecraft/client/Minecraft.gameMode:Lnet/minecraft/client/multiplayer/MultiPlayerGameMode;
       7: iload_1
       8: iload_2
       9: iload_3
      10: invokevirtual #719                // Method net/minecraft/client/multiplayer/MultiPlayerGameMode.handleSlotStateChanged:(IIZ)V
      13: return

  public boolean keyPressed(net.minecraft.client.input.KeyEvent);
    Code:
       0: aload_1
       1: invokestatic  #723                // Method com/mojang/blaze3d/platform/InputConstants.getKey:(Lnet/minecraft/client/input/KeyEvent;)Lcom/mojang/blaze3d/platform/InputConstants$Key;
       4: astore_2
       5: aload_0
       6: aload_1
       7: invokespecial #729                // Method net/minecraft/client/gui/screens/Screen.keyPressed:(Lnet/minecraft/client/input/KeyEvent;)Z
      10: ifeq          15
      13: iconst_1
      14: ireturn
      15: aload_0
      16: getfield      #99                 // Field minecraft:Lnet/minecraft/client/Minecraft;
      19: getfield      #542                // Field net/minecraft/client/Minecraft.options:Lnet/minecraft/client/Options;
      22: getfield      #733                // Field net/minecraft/client/Options.keyInventory:Lnet/minecraft/client/KeyMapping;
      25: aload_2
      26: invokevirtual #554                // Method net/minecraft/client/KeyMapping.isActiveAndMatches:(Lcom/mojang/blaze3d/platform/InputConstants$Key;)Z
      29: ifeq          38
      32: aload_0
      33: invokevirtual #596                // Method onClose:()V
      36: iconst_1
      37: ireturn
      38: aload_0
      39: aload_1
      40: invokevirtual #736                // Method checkHotbarKeyPressed:(Lnet/minecraft/client/input/KeyEvent;)Z
      43: istore_3
      44: aload_0
      45: getfield      #150                // Field hoveredSlot:Lnet/minecraft/world/inventory/Slot;
      48: ifnull        154
      51: aload_0
      52: getfield      #150                // Field hoveredSlot:Lnet/minecraft/world/inventory/Slot;
      55: invokevirtual #319                // Method net/minecraft/world/inventory/Slot.hasItem:()Z
      58: ifeq          154
      61: aload_0
      62: getfield      #99                 // Field minecraft:Lnet/minecraft/client/Minecraft;
      65: getfield      #542                // Field net/minecraft/client/Minecraft.options:Lnet/minecraft/client/Options;
      68: getfield      #548                // Field net/minecraft/client/Options.keyPickItem:Lnet/minecraft/client/KeyMapping;
      71: aload_2
      72: invokevirtual #554                // Method net/minecraft/client/KeyMapping.isActiveAndMatches:(Lcom/mojang/blaze3d/platform/InputConstants$Key;)Z
      75: ifeq          102
      78: aload_0
      79: aload_0
      80: getfield      #150                // Field hoveredSlot:Lnet/minecraft/world/inventory/Slot;
      83: aload_0
      84: getfield      #150                // Field hoveredSlot:Lnet/minecraft/world/inventory/Slot;
      87: getfield      #329                // Field net/minecraft/world/inventory/Slot.index:I
      90: iconst_0
      91: getstatic     #599                // Field net/minecraft/world/inventory/ContainerInput.CLONE:Lnet/minecraft/world/inventory/ContainerInput;
      94: invokevirtual #605                // Method slotClicked:(Lnet/minecraft/world/inventory/Slot;IILnet/minecraft/world/inventory/ContainerInput;)V
      97: iconst_1
      98: istore_3
      99: goto          173
     102: aload_0
     103: getfield      #99                 // Field minecraft:Lnet/minecraft/client/Minecraft;
     106: getfield      #542                // Field net/minecraft/client/Minecraft.options:Lnet/minecraft/client/Options;
     109: getfield      #739                // Field net/minecraft/client/Options.keyDrop:Lnet/minecraft/client/KeyMapping;
     112: aload_2
     113: invokevirtual #554                // Method net/minecraft/client/KeyMapping.isActiveAndMatches:(Lcom/mojang/blaze3d/platform/InputConstants$Key;)Z
     116: ifeq          173
     119: aload_0
     120: aload_0
     121: getfield      #150                // Field hoveredSlot:Lnet/minecraft/world/inventory/Slot;
     124: aload_0
     125: getfield      #150                // Field hoveredSlot:Lnet/minecraft/world/inventory/Slot;
     128: getfield      #329                // Field net/minecraft/world/inventory/Slot.index:I
     131: aload_1
     132: invokevirtual #742                // Method net/minecraft/client/input/KeyEvent.hasControlDown:()Z
     135: ifeq          142
     138: iconst_1
     139: goto          143
     142: iconst_0
     143: getstatic     #621                // Field net/minecraft/world/inventory/ContainerInput.THROW:Lnet/minecraft/world/inventory/ContainerInput;
     146: invokevirtual #605                // Method slotClicked:(Lnet/minecraft/world/inventory/Slot;IILnet/minecraft/world/inventory/ContainerInput;)V
     149: iconst_1
     150: istore_3
     151: goto          173
     154: aload_0
     155: getfield      #99                 // Field minecraft:Lnet/minecraft/client/Minecraft;
     158: getfield      #542                // Field net/minecraft/client/Minecraft.options:Lnet/minecraft/client/Options;
     161: getfield      #739                // Field net/minecraft/client/Options.keyDrop:Lnet/minecraft/client/KeyMapping;
     164: aload_2
     165: invokevirtual #554                // Method net/minecraft/client/KeyMapping.isActiveAndMatches:(Lcom/mojang/blaze3d/platform/InputConstants$Key;)Z
     168: ifeq          173
     171: iconst_1
     172: istore_3
     173: iload_3
     174: ireturn

  protected boolean checkHotbarKeyPressed(net.minecraft.client.input.KeyEvent);
    Code:
       0: aload_1
       1: invokestatic  #723                // Method com/mojang/blaze3d/platform/InputConstants.getKey:(Lnet/minecraft/client/input/KeyEvent;)Lcom/mojang/blaze3d/platform/InputConstants$Key;
       4: astore_2
       5: aload_0
       6: getfield      #34                 // Field menu:Lnet/minecraft/world/inventory/AbstractContainerMenu;
       9: invokevirtual #195                // Method net/minecraft/world/inventory/AbstractContainerMenu.getCarried:()Lnet/minecraft/world/item/ItemStack;
      12: invokevirtual #191                // Method net/minecraft/world/item/ItemStack.isEmpty:()Z
      15: ifeq          118
      18: aload_0
      19: getfield      #150                // Field hoveredSlot:Lnet/minecraft/world/inventory/Slot;
      22: ifnull        118
      25: aload_0
      26: getfield      #99                 // Field minecraft:Lnet/minecraft/client/Minecraft;
      29: getfield      #542                // Field net/minecraft/client/Minecraft.options:Lnet/minecraft/client/Options;
      32: getfield      #628                // Field net/minecraft/client/Options.keySwapOffhand:Lnet/minecraft/client/KeyMapping;
      35: aload_2
      36: invokevirtual #554                // Method net/minecraft/client/KeyMapping.isActiveAndMatches:(Lcom/mojang/blaze3d/platform/InputConstants$Key;)Z
      39: ifeq          64
      42: aload_0
      43: aload_0
      44: getfield      #150                // Field hoveredSlot:Lnet/minecraft/world/inventory/Slot;
      47: aload_0
      48: getfield      #150                // Field hoveredSlot:Lnet/minecraft/world/inventory/Slot;
      51: getfield      #329                // Field net/minecraft/world/inventory/Slot.index:I
      54: bipush        40
      56: getstatic     #635                // Field net/minecraft/world/inventory/ContainerInput.SWAP:Lnet/minecraft/world/inventory/ContainerInput;
      59: invokevirtual #605                // Method slotClicked:(Lnet/minecraft/world/inventory/Slot;IILnet/minecraft/world/inventory/ContainerInput;)V
      62: iconst_1
      63: ireturn
      64: iconst_0
      65: istore_3
      66: iload_3
      67: bipush        9
      69: if_icmpge     118
      72: aload_0
      73: getfield      #99                 // Field minecraft:Lnet/minecraft/client/Minecraft;
      76: getfield      #542                // Field net/minecraft/client/Minecraft.options:Lnet/minecraft/client/Options;
      79: getfield      #638                // Field net/minecraft/client/Options.keyHotbarSlots:[Lnet/minecraft/client/KeyMapping;
      82: iload_3
      83: aaload
      84: aload_2
      85: invokevirtual #554                // Method net/minecraft/client/KeyMapping.isActiveAndMatches:(Lcom/mojang/blaze3d/platform/InputConstants$Key;)Z
      88: ifeq          112
      91: aload_0
      92: aload_0
      93: getfield      #150                // Field hoveredSlot:Lnet/minecraft/world/inventory/Slot;
      96: aload_0
      97: getfield      #150                // Field hoveredSlot:Lnet/minecraft/world/inventory/Slot;
     100: getfield      #329                // Field net/minecraft/world/inventory/Slot.index:I
     103: iload_3
     104: getstatic     #635                // Field net/minecraft/world/inventory/ContainerInput.SWAP:Lnet/minecraft/world/inventory/ContainerInput;
     107: invokevirtual #605                // Method slotClicked:(Lnet/minecraft/world/inventory/Slot;IILnet/minecraft/world/inventory/ContainerInput;)V
     110: iconst_1
     111: ireturn
     112: iinc          3, 1
     115: goto          66
     118: iconst_0
     119: ireturn

  public void removed();
    Code:
       0: aload_0
       1: getfield      #99                 // Field minecraft:Lnet/minecraft/client/Minecraft;
       4: getfield      #560                // Field net/minecraft/client/Minecraft.player:Lnet/minecraft/client/player/LocalPlayer;
       7: ifnull        24
      10: aload_0
      11: getfield      #34                 // Field menu:Lnet/minecraft/world/inventory/AbstractContainerMenu;
      14: aload_0
      15: getfield      #99                 // Field minecraft:Lnet/minecraft/client/Minecraft;
      18: getfield      #560                // Field net/minecraft/client/Minecraft.player:Lnet/minecraft/client/player/LocalPlayer;
      21: invokevirtual #747                // Method net/minecraft/world/inventory/AbstractContainerMenu.removed:(Lnet/minecraft/world/entity/player/Player;)V
      24: return

  public boolean isPauseScreen();
    Code:
       0: iconst_0
       1: ireturn

  public boolean isInGameUi();
    Code:
       0: iconst_1
       1: ireturn

  public final void tick();
    Code:
       0: aload_0
       1: invokespecial #751                // Method net/minecraft/client/gui/screens/Screen.tick:()V
       4: aload_0
       5: getfield      #99                 // Field minecraft:Lnet/minecraft/client/Minecraft;
       8: getfield      #560                // Field net/minecraft/client/Minecraft.player:Lnet/minecraft/client/player/LocalPlayer;
      11: invokevirtual #754                // Method net/minecraft/client/player/LocalPlayer.isAlive:()Z
      14: ifeq          37
      17: aload_0
      18: getfield      #99                 // Field minecraft:Lnet/minecraft/client/Minecraft;
      21: getfield      #560                // Field net/minecraft/client/Minecraft.player:Lnet/minecraft/client/player/LocalPlayer;
      24: invokevirtual #757                // Method net/minecraft/client/player/LocalPlayer.isRemoved:()Z
      27: ifne          37
      30: aload_0
      31: invokevirtual #760                // Method containerTick:()V
      34: goto          47
      37: aload_0
      38: getfield      #99                 // Field minecraft:Lnet/minecraft/client/Minecraft;
      41: getfield      #560                // Field net/minecraft/client/Minecraft.player:Lnet/minecraft/client/player/LocalPlayer;
      44: invokevirtual #763                // Method net/minecraft/client/player/LocalPlayer.closeContainer:()V
      47: return

  protected void containerTick();
    Code:
       0: return

  public T getMenu();
    Code:
       0: aload_0
       1: getfield      #34                 // Field menu:Lnet/minecraft/world/inventory/AbstractContainerMenu;
       4: areturn

  public net.minecraft.world.inventory.Slot getHoveredSlot();
    Code:
       0: aload_0
       1: getfield      #150                // Field hoveredSlot:Lnet/minecraft/world/inventory/Slot;
       4: areturn

  public int getLeftPos();
    Code:
       0: aload_0
       1: getfield      #83                 // Field leftPos:I
       4: ireturn

  public int getTopPos();
    Code:
       0: aload_0
       1: getfield      #89                 // Field topPos:I
       4: ireturn

  public int getImageWidth();
    Code:
       0: aload_0
       1: getfield      #48                 // Field imageWidth:I
       4: ireturn

  public int getImageHeight();
    Code:
       0: aload_0
       1: getfield      #52                 // Field imageHeight:I
       4: ireturn

  public net.minecraft.world.inventory.Slot getSlotUnderMouse();
    Code:
       0: aload_0
       1: invokevirtual #775                // Method getHoveredSlot:()Lnet/minecraft/world/inventory/Slot;
       4: areturn

  public int getGuiLeft();
    Code:
       0: aload_0
       1: invokevirtual #778                // Method getLeftPos:()I
       4: ireturn

  public int getGuiTop();
    Code:
       0: aload_0
       1: invokevirtual #781                // Method getTopPos:()I
       4: ireturn

  public int getXSize();
    Code:
       0: aload_0
       1: invokevirtual #784                // Method getImageWidth:()I
       4: ireturn

  public int getYSize();
    Code:
       0: aload_0
       1: invokevirtual #787                // Method getImageHeight:()I
       4: ireturn

  public void onClose();
    Code:
       0: aload_0
       1: getfield      #99                 // Field minecraft:Lnet/minecraft/client/Minecraft;
       4: getfield      #560                // Field net/minecraft/client/Minecraft.player:Lnet/minecraft/client/player/LocalPlayer;
       7: invokevirtual #763                // Method net/minecraft/client/player/LocalPlayer.closeContainer:()V
      10: aload_0
      11: getfield      #150                // Field hoveredSlot:Lnet/minecraft/world/inventory/Slot;
      14: ifnull        25
      17: aload_0
      18: aload_0
      19: getfield      #150                // Field hoveredSlot:Lnet/minecraft/world/inventory/Slot;
      22: invokevirtual #167                // Method onStopHovering:(Lnet/minecraft/world/inventory/Slot;)V
      25: aload_0
      26: invokespecial #790                // Method net/minecraft/client/gui/screens/Screen.onClose:()V
      29: return

  static {};
    Code:
       0: ldc_w         #791                // String textures/gui/container/inventory.png
       3: invokestatic  #793                // Method net/minecraft/resources/Identifier.withDefaultNamespace:(Ljava/lang/String;)Lnet/minecraft/resources/Identifier;
       6: putstatic     #797                // Field INVENTORY_LOCATION:Lnet/minecraft/resources/Identifier;
       9: ldc_w         #800                // String container/slot_highlight_back
      12: invokestatic  #793                // Method net/minecraft/resources/Identifier.withDefaultNamespace:(Ljava/lang/String;)Lnet/minecraft/resources/Identifier;
      15: putstatic     #348                // Field SLOT_HIGHLIGHT_BACK_SPRITE:Lnet/minecraft/resources/Identifier;
      18: ldc_w         #802                // String container/slot_highlight_front
      21: invokestatic  #793                // Method net/minecraft/resources/Identifier.withDefaultNamespace:(Ljava/lang/String;)Lnet/minecraft/resources/Identifier;
      24: putstatic     #358                // Field SLOT_HIGHLIGHT_FRONT_SPRITE:Lnet/minecraft/resources/Identifier;
      27: return
}
